{
"meta":{"test_sets":[],"test_metrics":[],"learn_metrics":[{"best_value":"Min","name":"Logloss"}],"launch_mode":"Train","parameters":"","iteration_count":1000,"learn_sets":["learn"],"name":"experiment"},
"iterations":[
{"learn":[0.6233457486],"iteration":0,"passed_time":0.07168070359,"remaining_time":71.60902289},
{"learn":[0.5700638244],"iteration":1,"passed_time":0.08135016818,"remaining_time":40.59373392},
{"learn":[0.5193263164],"iteration":2,"passed_time":0.0976997195,"remaining_time":32.46887345},
{"learn":[0.4625914011],"iteration":3,"passed_time":0.1043945879,"remaining_time":25.9942524},
{"learn":[0.418208221],"iteration":4,"passed_time":0.1189474533,"remaining_time":23.67054322},
{"learn":[0.3808712194],"iteration":5,"passed_time":0.137302474,"remaining_time":22.7464432},
{"learn":[0.3502082339],"iteration":6,"passed_time":0.1479928168,"remaining_time":20.99383816},
{"learn":[0.3195308521],"iteration":7,"passed_time":0.1616467059,"remaining_time":20.04419153},
{"learn":[0.2931398894],"iteration":8,"passed_time":0.1685123772,"remaining_time":18.55508509},
{"learn":[0.2647549105],"iteration":9,"passed_time":0.1864054217,"remaining_time":18.45413675},
{"learn":[0.2424906533],"iteration":10,"passed_time":0.2097923155,"remaining_time":18.86223636},
{"learn":[0.2200769683],"iteration":11,"passed_time":0.2229638673,"remaining_time":18.3573584},
{"learn":[0.1992042465],"iteration":12,"passed_time":0.2372555357,"remaining_time":18.01317029},
{"learn":[0.1793325454],"iteration":13,"passed_time":0.2483187761,"remaining_time":17.48873666},
{"learn":[0.1642865959],"iteration":14,"passed_time":0.262229261,"remaining_time":17.21972147},
{"learn":[0.1532666043],"iteration":15,"passed_time":0.2676376312,"remaining_time":16.45971432},
{"learn":[0.1396678499],"iteration":16,"passed_time":0.2945103995,"remaining_time":17.02963075},
{"learn":[0.1285548887],"iteration":17,"passed_time":0.3092667047,"remaining_time":16.87221689},
{"learn":[0.1179414822],"iteration":18,"passed_time":0.3232255874,"remaining_time":16.68864743},
{"learn":[0.1084087718],"iteration":19,"passed_time":0.3387462575,"remaining_time":16.59856662},
{"learn":[0.09926720937],"iteration":20,"passed_time":0.3501449837,"remaining_time":16.32342567},
{"learn":[0.09234990518],"iteration":21,"passed_time":0.36471698,"remaining_time":16.21332756},
{"learn":[0.08538775843],"iteration":22,"passed_time":0.3789389376,"remaining_time":16.09666705},
{"learn":[0.07929278033],"iteration":23,"passed_time":0.3941311159,"remaining_time":16.02799871},
{"learn":[0.0727891217],"iteration":24,"passed_time":0.4031014945,"remaining_time":15.72095828},
{"learn":[0.06762771232],"iteration":25,"passed_time":0.411604014,"remaining_time":15.4193196},
{"learn":[0.06214289235],"iteration":26,"passed_time":0.4185123438,"remaining_time":15.08194483},
{"learn":[0.0587785976],"iteration":27,"passed_time":0.4224527289,"remaining_time":14.66514473},
{"learn":[0.05465886312],"iteration":28,"passed_time":0.4267069731,"remaining_time":14.28732658},
{"learn":[0.05108096131],"iteration":29,"passed_time":0.4302850993,"remaining_time":13.91255154},
{"learn":[0.04782037366],"iteration":30,"passed_time":0.4357937016,"remaining_time":13.62206764},
{"learn":[0.04434677037],"iteration":31,"passed_time":0.4413351685,"remaining_time":13.35038885},
{"learn":[0.04130192168],"iteration":32,"passed_time":0.4468917092,"remaining_time":13.0952813},
{"learn":[0.03824222334],"iteration":33,"passed_time":0.4525279599,"remaining_time":12.85711792},
{"learn":[0.03565661842],"iteration":34,"passed_time":0.4581787977,"remaining_time":12.63264399},
{"learn":[0.03361654513],"iteration":35,"passed_time":0.4635797255,"remaining_time":12.41363487},
{"learn":[0.03178639755],"iteration":36,"passed_time":0.517666817,"remaining_time":13.47332824},
{"learn":[0.02990179921],"iteration":37,"passed_time":0.5582297044,"remaining_time":14.13202567},
{"learn":[0.02784771357],"iteration":38,"passed_time":0.5719895704,"remaining_time":14.09440967},
{"learn":[0.02623096875],"iteration":39,"passed_time":0.5776909684,"remaining_time":13.86458324},
{"learn":[0.02424685649],"iteration":40,"passed_time":0.583272217,"remaining_time":13.64287942},
{"learn":[0.02280759972],"iteration":41,"passed_time":0.5889294645,"remaining_time":13.43320064},
{"learn":[0.02140982883],"iteration":42,"passed_time":0.5945565725,"remaining_time":13.23234046},
{"learn":[0.02020850821],"iteration":43,"passed_time":0.6012300817,"remaining_time":13.06308996},
{"learn":[0.01889495278],"iteration":44,"passed_time":0.6051161061,"remaining_time":12.84190847},
{"learn":[0.01785171114],"iteration":45,"passed_time":0.6146169103,"remaining_time":12.74662027},
{"learn":[0.0165527356],"iteration":46,"passed_time":0.6274791201,"remaining_time":12.72314046},
{"learn":[0.01570510378],"iteration":47,"passed_time":0.6478900649,"remaining_time":12.84981962},
{"learn":[0.01462892661],"iteration":48,"passed_time":0.6658206193,"remaining_time":12.92235528},
{"learn":[0.01368099547],"iteration":49,"passed_time":0.6812750176,"remaining_time":12.94422533},
{"learn":[0.0127947801],"iteration":50,"passed_time":0.6957461083,"remaining_time":12.94633445},
{"learn":[0.01210872094],"iteration":51,"passed_time":0.710658652,"remaining_time":12.95585389},
{"learn":[0.01149793398],"iteration":52,"passed_time":0.7162347554,"remaining_time":12.79762855},
{"learn":[0.01092323563],"iteration":53,"passed_time":0.725754289,"remaining_time":12.71413995},
{"learn":[0.01037693946],"iteration":54,"passed_time":0.7321672042,"remaining_time":12.57996378},
{"learn":[0.009863325611],"iteration":55,"passed_time":0.7383760197,"remaining_time":12.44691005},
{"learn":[0.009375753729],"iteration":56,"passed_time":0.7494142337,"remaining_time":12.3982039},
{"learn":[0.008878434242],"iteration":57,"passed_time":0.7568102047,"remaining_time":12.2916416},
{"learn":[0.008438072269],"iteration":58,"passed_time":0.7619090622,"remaining_time":12.15180386},
{"learn":[0.00802891328],"iteration":59,"passed_time":0.7654883602,"remaining_time":11.99265098},
{"learn":[0.007632917943],"iteration":60,"passed_time":0.7697409824,"remaining_time":11.84896365},
{"learn":[0.007254216275],"iteration":61,"passed_time":0.7813957523,"remaining_time":11.82176154},
{"learn":[0.006912321938],"iteration":62,"passed_time":0.79654139,"remaining_time":11.84697274},
{"learn":[0.006648966466],"iteration":63,"passed_time":0.8066339699,"remaining_time":11.79702181},
{"learn":[0.006286001179],"iteration":64,"passed_time":0.8172361104,"remaining_time":11.75562713},
{"learn":[0.006038907203],"iteration":65,"passed_time":0.8305650184,"remaining_time":11.75375344},
{"learn":[0.005807403944],"iteration":66,"passed_time":0.8471069329,"remaining_time":11.79628013},
{"learn":[0.005592643814],"iteration":67,"passed_time":0.8577896715,"remaining_time":11.75676432},
{"learn":[0.005389533119],"iteration":68,"passed_time":0.8732734847,"remaining_time":11.78286397},
{"learn":[0.005143199609],"iteration":69,"passed_time":0.8868512373,"remaining_time":11.78245215},
{"learn":[0.004965258526],"iteration":70,"passed_time":0.8997378807,"remaining_time":11.77262664},
{"learn":[0.004779713869],"iteration":71,"passed_time":0.910483567,"remaining_time":11.73512153},
{"learn":[0.004615135091],"iteration":72,"passed_time":0.9264485499,"remaining_time":11.76462748},
{"learn":[0.004454064174],"iteration":73,"passed_time":0.937977574,"remaining_time":11.73739505},
{"learn":[0.004302351138],"iteration":74,"passed_time":0.9501935067,"remaining_time":11.71905325},
{"learn":[0.004167259827],"iteration":75,"passed_time":0.963524936,"remaining_time":11.71443475},
{"learn":[0.004010756245],"iteration":76,"passed_time":0.9759991348,"remaining_time":11.6993143},
{"learn":[0.003872913117],"iteration":77,"passed_time":0.9913210052,"remaining_time":11.71792265},
{"learn":[0.003772130504],"iteration":78,"passed_time":1.006595598,"remaining_time":11.73512084},
{"learn":[0.003649966243],"iteration":79,"passed_time":1.017153523,"remaining_time":11.69726552},
{"learn":[0.003535183955],"iteration":80,"passed_time":1.031319299,"remaining_time":11.70101773},
{"learn":[0.003437879985],"iteration":81,"passed_time":1.046497409,"remaining_time":11.71566612},
{"learn":[0.003348439669],"iteration":82,"passed_time":1.060106075,"remaining_time":11.71225627},
{"learn":[0.003239162104],"iteration":83,"passed_time":1.078584751,"remaining_time":11.76170991},
{"learn":[0.003153764467],"iteration":84,"passed_time":1.084158568,"remaining_time":11.67064812},
{"learn":[0.003070358126],"iteration":85,"passed_time":1.088089585,"remaining_time":11.56411489},
{"learn":[0.002996516367],"iteration":86,"passed_time":1.100860307,"remaining_time":11.55270644},
{"learn":[0.002917943215],"iteration":87,"passed_time":1.113511697,"remaining_time":11.54003031},
{"learn":[0.00283566353],"iteration":88,"passed_time":1.121265372,"remaining_time":11.47722195},
{"learn":[0.002754162714],"iteration":89,"passed_time":1.128107222,"remaining_time":11.40641747},
{"learn":[0.002687272296],"iteration":90,"passed_time":1.136144566,"remaining_time":11.34896056},
{"learn":[0.002633939486],"iteration":91,"passed_time":1.144542548,"remaining_time":11.29613732},
{"learn":[0.002570313558],"iteration":92,"passed_time":1.152931279,"remaining_time":11.24417924},
{"learn":[0.00250476386],"iteration":93,"passed_time":1.162058093,"remaining_time":11.20026205},
{"learn":[0.002448986966],"iteration":94,"passed_time":1.168120316,"remaining_time":11.12788301},
{"learn":[0.002377690648],"iteration":95,"passed_time":1.179772404,"remaining_time":11.10952347},
{"learn":[0.002325760783],"iteration":96,"passed_time":1.193379615,"remaining_time":11.10950302},
{"learn":[0.002278987566],"iteration":97,"passed_time":1.204246736,"remaining_time":11.08398526},
{"learn":[0.002233968622],"iteration":98,"passed_time":1.219356423,"remaining_time":11.09737513},
{"learn":[0.002195548347],"iteration":99,"passed_time":1.229971928,"remaining_time":11.06974735},
{"learn":[0.002155806897],"iteration":100,"passed_time":1.244073914,"remaining_time":11.0734896},
{"learn":[0.002115779351],"iteration":101,"passed_time":1.259326425,"remaining_time":11.08701108},
{"learn":[0.002083534443],"iteration":102,"passed_time":1.267139375,"remaining_time":11.03518466},
{"learn":[0.002051530297],"iteration":103,"passed_time":1.276663772,"remaining_time":10.99894942},
{"learn":[0.002011122767],"iteration":104,"passed_time":1.286592223,"remaining_time":10.96666704},
{"learn":[0.001961257363],"iteration":105,"passed_time":1.298137181,"remaining_time":10.94844},
{"learn":[0.001929633402],"iteration":106,"passed_time":1.310490364,"remaining_time":10.93708313},
{"learn":[0.001899576803],"iteration":107,"passed_time":1.321815477,"remaining_time":10.91721672},
{"learn":[0.001865325353],"iteration":108,"passed_time":1.337618486,"remaining_time":10.93411074},
{"learn":[0.001838218049],"iteration":109,"passed_time":1.346918779,"remaining_time":10.89779739},
{"learn":[0.001804636432],"iteration":110,"passed_time":1.357555425,"remaining_time":10.87267363},
{"learn":[0.001761917941],"iteration":111,"passed_time":1.362217158,"remaining_time":10.80043604},
{"learn":[0.001736523572],"iteration":112,"passed_time":1.373380002,"remaining_time":10.78042533},
{"learn":[0.001713944515],"iteration":113,"passed_time":1.378691384,"remaining_time":10.71509269},
{"learn":[0.001686263857],"iteration":114,"passed_time":1.398836882,"remaining_time":10.76496209},
{"learn":[0.001656549838],"iteration":115,"passed_time":1.41115423,"remaining_time":10.75396844},
{"learn":[0.001630646983],"iteration":116,"passed_time":1.419008848,"remaining_time":10.70927191},
{"learn":[0.001609068726],"iteration":117,"passed_time":1.43421408,"remaining_time":10.72014253},
{"learn":[0.001580644565],"iteration":118,"passed_time":1.440982176,"remaining_time":10.66811174},
{"learn":[0.001553760025],"iteration":119,"passed_time":1.448737358,"remaining_time":10.62407396},
{"learn":[0.001533536166],"iteration":120,"passed_time":1.454724545,"remaining_time":10.56779236},
{"learn":[0.001506523812],"iteration":121,"passed_time":1.460333457,"remaining_time":10.50961291},
{"learn":[0.001477074354],"iteration":122,"passed_time":1.470439587,"remaining_time":10.48435381},
{"learn":[0.001444488476],"iteration":123,"passed_time":1.484247839,"remaining_time":10.4854928},
{"learn":[0.00140513326],"iteration":124,"passed_time":1.501450325,"remaining_time":10.51015227},
{"learn":[0.001382104771],"iteration":125,"passed_time":1.510102321,"remaining_time":10.47483673},
{"learn":[0.001363006681],"iteration":126,"passed_time":1.523108936,"remaining_time":10.46987481},
{"learn":[0.001345756562],"iteration":127,"passed_time":1.528439976,"remaining_time":10.41249733},
{"learn":[0.001329026009],"iteration":128,"passed_time":1.534022629,"remaining_time":10.35762566},
{"learn":[0.001309603345],"iteration":129,"passed_time":1.563585882,"remaining_time":10.46399782},
{"learn":[0.001293865249],"iteration":130,"passed_time":1.569598031,"remaining_time":10.41206633},
{"learn":[0.001273241338],"iteration":131,"passed_time":1.582588125,"remaining_time":10.40671585},
{"learn":[0.001258477063],"iteration":132,"passed_time":1.597889757,"remaining_time":10.41631894},
{"learn":[0.001232143066],"iteration":133,"passed_time":1.608860042,"remaining_time":10.39755818},
{"learn":[0.001208856185],"iteration":134,"passed_time":1.619547298,"remaining_time":10.37709936},
{"learn":[0.001196751867],"iteration":135,"passed_time":1.640502255,"remaining_time":10.42201432},
{"learn":[0.00118160894],"iteration":136,"passed_time":1.660110538,"remaining_time":10.45748463},
{"learn":[0.001160753359],"iteration":137,"passed_time":1.678540313,"remaining_time":10.48479529},
{"learn":[0.001143381628],"iteration":138,"passed_time":1.687259195,"remaining_time":10.45129616},
{"learn":[0.001131785077],"iteration":139,"passed_time":1.693288813,"remaining_time":10.40163128},
{"learn":[0.001117028586],"iteration":140,"passed_time":1.69891629,"remaining_time":10.35013541},
{"learn":[0.001103533925],"iteration":141,"passed_time":1.708281389,"remaining_time":10.32186924},
{"learn":[0.001092957524],"iteration":142,"passed_time":1.720158013,"remaining_time":10.308919},
{"learn":[0.001080346911],"iteration":143,"passed_time":1.727675212,"remaining_time":10.27006931},
{"learn":[0.001068298033],"iteration":144,"passed_time":1.739665757,"remaining_time":10.25802912},
{"learn":[0.001050943744],"iteration":145,"passed_time":1.757227421,"remaining_time":10.27857683},
{"learn":[0.001041962716],"iteration":146,"passed_time":1.768578687,"remaining_time":10.26256884},
{"learn":[0.001029948405],"iteration":147,"passed_time":1.785700975,"remaining_time":10.27984615},
{"learn":[0.001019219296],"iteration":148,"passed_time":1.792850717,"remaining_time":10.23970443},
{"learn":[0.001004707946],"iteration":149,"passed_time":1.810297724,"remaining_time":10.25835377},
{"learn":[0.0009962665849],"iteration":150,"passed_time":1.828824307,"remaining_time":10.28259495},
{"learn":[0.0009835025226],"iteration":151,"passed_time":1.848076741,"remaining_time":10.31032287},
{"learn":[0.0009733807941],"iteration":152,"passed_time":1.865594983,"remaining_time":10.32783628},
{"learn":[0.0009621478722],"iteration":153,"passed_time":1.880230612,"remaining_time":10.32905908},
{"learn":[0.0009505871454],"iteration":154,"passed_time":1.892434177,"remaining_time":10.31681858},
{"learn":[0.0009407937564],"iteration":155,"passed_time":1.901639341,"remaining_time":10.28835643},
{"learn":[0.0009309099184],"iteration":156,"passed_time":1.913165894,"remaining_time":10.27260413},
{"learn":[0.0009222076648],"iteration":157,"passed_time":1.931187156,"remaining_time":10.29151636},
{"learn":[0.0009141581683],"iteration":158,"passed_time":1.948199033,"remaining_time":10.30462507},
{"learn":[0.0009031167083],"iteration":159,"passed_time":1.961088135,"remaining_time":10.29571271},
{"learn":[0.0008961579218],"iteration":160,"passed_time":1.970454842,"remaining_time":10.26839511},
{"learn":[0.0008847079282],"iteration":161,"passed_time":1.982681145,"remaining_time":10.25609135},
{"learn":[0.0008761117541],"iteration":162,"passed_time":2.000098222,"remaining_time":10.27044302},
{"learn":[0.0008646780264],"iteration":163,"passed_time":2.017481107,"remaining_time":10.28423296},
{"learn":[0.0008545430176],"iteration":164,"passed_time":2.031852243,"remaining_time":10.28240378},
{"learn":[0.0008452176312],"iteration":165,"passed_time":2.044931333,"remaining_time":10.27393212},
{"learn":[0.0008452081522],"iteration":166,"passed_time":2.059888694,"remaining_time":10.27477414},
{"learn":[0.0008375688517],"iteration":167,"passed_time":2.070829092,"remaining_time":10.25553455},
{"learn":[0.0008308477527],"iteration":168,"passed_time":2.0795897,"remaining_time":10.2256748},
{"learn":[0.0008202605735],"iteration":169,"passed_time":2.095980929,"remaining_time":10.23331865},
{"learn":[0.0008117386599],"iteration":170,"passed_time":2.105790325,"remaining_time":10.20877298},
{"learn":[0.0007958849324],"iteration":171,"passed_time":2.118046032,"remaining_time":10.19617508},
{"learn":[0.0007898698156],"iteration":172,"passed_time":2.128894643,"remaining_time":10.17685474},
{"learn":[0.0007825633766],"iteration":173,"passed_time":2.141639185,"remaining_time":10.16663199},
{"learn":[0.0007747671726],"iteration":174,"passed_time":2.1546191,"remaining_time":10.15749004},
{"learn":[0.0007747767672],"iteration":175,"passed_time":2.162577914,"remaining_time":10.1247966},
{"learn":[0.0007680262144],"iteration":176,"passed_time":2.172480462,"remaining_time":10.10142045},
{"learn":[0.0007599527539],"iteration":177,"passed_time":2.177104053,"remaining_time":10.05381759},
{"learn":[0.0007468984581],"iteration":178,"passed_time":2.189489576,"remaining_time":10.04229577},
{"learn":[0.0007390593178],"iteration":179,"passed_time":2.201264428,"remaining_time":10.02798239},
{"learn":[0.0007318834715],"iteration":180,"passed_time":2.214215877,"remaining_time":10.01902101},
{"learn":[0.0007318766781],"iteration":181,"passed_time":2.236624976,"remaining_time":10.05252324},
{"learn":[0.0007318617125],"iteration":182,"passed_time":2.245599887,"remaining_time":10.02543775},
{"learn":[0.0007234627733],"iteration":183,"passed_time":2.249568433,"remaining_time":9.976346962},
{"learn":[0.000715599055],"iteration":184,"passed_time":2.257106702,"remaining_time":9.943470066},
{"learn":[0.0007156064842],"iteration":185,"passed_time":2.268109721,"remaining_time":9.926028563},
{"learn":[0.0007144363182],"iteration":186,"passed_time":2.279706245,"remaining_time":9.911236242},
{"learn":[0.0007043833258],"iteration":187,"passed_time":2.289715842,"remaining_time":9.889623743},
{"learn":[0.0006971156023],"iteration":188,"passed_time":2.305550243,"remaining_time":9.893128291},
{"learn":[0.0006899778987],"iteration":189,"passed_time":2.318642332,"remaining_time":9.884738363},
{"learn":[0.0006899658765],"iteration":190,"passed_time":2.331878039,"remaining_time":9.876907506},
{"learn":[0.0006899728969],"iteration":191,"passed_time":2.336551884,"remaining_time":9.83298918},
{"learn":[0.0006899722612],"iteration":192,"passed_time":2.348363507,"remaining_time":9.819323056},
{"learn":[0.0006899617418],"iteration":193,"passed_time":2.35692996,"remaining_time":9.792193546},
{"learn":[0.0006899617418],"iteration":194,"passed_time":2.362051369,"remaining_time":9.751032574},
{"learn":[0.0006899639382],"iteration":195,"passed_time":2.367217644,"remaining_time":9.710423396},
{"learn":[0.0006812470494],"iteration":196,"passed_time":2.372425722,"remaining_time":9.670344441},
{"learn":[0.0006803017467],"iteration":197,"passed_time":2.377870474,"remaining_time":9.631576363},
{"learn":[0.0006803017467],"iteration":198,"passed_time":2.382876449,"remaining_time":9.591377063},
{"learn":[0.0006699742109],"iteration":199,"passed_time":2.388159014,"remaining_time":9.552636057},
{"learn":[0.0006699742109],"iteration":200,"passed_time":2.393434996,"remaining_time":9.514201799},
{"learn":[0.0006699742109],"iteration":201,"passed_time":2.39862368,"remaining_time":9.475750973},
{"learn":[0.0006643129533],"iteration":202,"passed_time":2.4326591,"remaining_time":9.550883266},
{"learn":[0.0006643043724],"iteration":203,"passed_time":2.439573972,"remaining_time":9.519121968},
{"learn":[0.0006554342551],"iteration":204,"passed_time":2.443622949,"remaining_time":9.476488997},
{"learn":[0.000653935693],"iteration":205,"passed_time":2.449713042,"remaining_time":9.442097842},
{"learn":[0.0006539173131],"iteration":206,"passed_time":2.462341254,"remaining_time":9.433027121},
{"learn":[0.000645257587],"iteration":207,"passed_time":2.471247712,"remaining_time":9.409750902},
{"learn":[0.000645231462],"iteration":208,"passed_time":2.481812884,"remaining_time":9.392889909},
{"learn":[0.0006452189507],"iteration":209,"passed_time":2.492630721,"remaining_time":9.377039381},
{"learn":[0.0006452363749],"iteration":210,"passed_time":2.50671165,"remaining_time":9.37343835},
{"learn":[0.000645223428],"iteration":211,"passed_time":2.511970845,"remaining_time":9.336948236},
{"learn":[0.0006452171857],"iteration":212,"passed_time":2.517359527,"remaining_time":9.301229803},
{"learn":[0.0006452205959],"iteration":213,"passed_time":2.522380464,"remaining_time":9.264444134},
{"learn":[0.0006452175946],"iteration":214,"passed_time":2.527691458,"remaining_time":9.229012996},
{"learn":[0.000645213371],"iteration":215,"passed_time":2.584551168,"remaining_time":9.380963498},
{"learn":[0.0006452178793],"iteration":216,"passed_time":2.59103962,"remaining_time":9.349235128},
{"learn":[0.0006451957425],"iteration":217,"passed_time":2.600199108,"remaining_time":9.327319736},
{"learn":[0.0006452058037],"iteration":218,"passed_time":2.607373357,"remaining_time":9.298441058},
{"learn":[0.0006432157512],"iteration":219,"passed_time":2.633024833,"remaining_time":9.335269864},
{"learn":[0.0006432157512],"iteration":220,"passed_time":2.641739716,"remaining_time":9.311833659},
{"learn":[0.0006432089577],"iteration":221,"passed_time":2.665116286,"remaining_time":9.339912029},
{"learn":[0.0006432258082],"iteration":222,"passed_time":2.673412056,"remaining_time":9.314982815},
{"learn":[0.0006432258082],"iteration":223,"passed_time":2.67868932,"remaining_time":9.279745146},
{"learn":[0.0006431966199],"iteration":224,"passed_time":2.684133969,"remaining_time":9.245350338},
{"learn":[0.0006431929786],"iteration":225,"passed_time":2.689470856,"remaining_time":9.210842667},
{"learn":[0.000635660105],"iteration":226,"passed_time":2.695212586,"remaining_time":9.177970612},
{"learn":[0.0006356528802],"iteration":227,"passed_time":2.700390972,"remaining_time":9.14342908},
{"learn":[0.0006356530268],"iteration":228,"passed_time":2.70526441,"remaining_time":9.108117294},
{"learn":[0.000635645513],"iteration":229,"passed_time":2.760243916,"remaining_time":9.240816589},
{"learn":[0.0006356412359],"iteration":230,"passed_time":2.790858968,"remaining_time":9.290781585},
{"learn":[0.0006356439257],"iteration":231,"passed_time":2.803775458,"remaining_time":9.281463586},
{"learn":[0.0006356439257],"iteration":232,"passed_time":2.808887753,"remaining_time":9.246424491},
{"learn":[0.0006356545563],"iteration":233,"passed_time":2.813989984,"remaining_time":9.211608237},
{"learn":[0.0006356451662],"iteration":234,"passed_time":2.819227635,"remaining_time":9.177485704},
{"learn":[0.0006356451662],"iteration":235,"passed_time":2.876935131,"remaining_time":9.313467967},
{"learn":[0.000635652422],"iteration":236,"passed_time":2.89576214,"remaining_time":9.322643514},
{"learn":[0.0006356387773],"iteration":237,"passed_time":2.908025641,"remaining_time":9.310569489},
{"learn":[0.0006356347624],"iteration":238,"passed_time":2.911537563,"remaining_time":9.270627973},
{"learn":[0.0006356363808],"iteration":239,"passed_time":2.917377066,"remaining_time":9.238360708},
{"learn":[0.0006356324505],"iteration":240,"passed_time":2.922511183,"remaining_time":9.204091237},
{"learn":[0.0006356324505],"iteration":241,"passed_time":2.927546616,"remaining_time":9.169753451},
{"learn":[0.0006356233761],"iteration":242,"passed_time":2.971005916,"remaining_time":9.255355877},
{"learn":[0.0006356219001],"iteration":243,"passed_time":2.992839121,"remaining_time":9.272894982},
{"learn":[0.0006265452372],"iteration":244,"passed_time":3.00178028,"remaining_time":9.250384127},
{"learn":[0.0006265470868],"iteration":245,"passed_time":3.006911843,"remaining_time":9.216307031},
{"learn":[0.0006265434187],"iteration":246,"passed_time":3.012111984,"remaining_time":9.182673375},
{"learn":[0.0006265494565],"iteration":247,"passed_time":3.036922401,"remaining_time":9.208732442},
{"learn":[0.0006265306142],"iteration":248,"passed_time":3.040208505,"remaining_time":9.169464205},
{"learn":[0.0006265346291],"iteration":249,"passed_time":3.057602458,"remaining_time":9.172807373},
{"learn":[0.0006265313388],"iteration":250,"passed_time":3.070083945,"remaining_time":9.161326194},
{"learn":[0.0006265156443],"iteration":251,"passed_time":3.078316933,"remaining_time":9.137226453},
{"learn":[0.0006265182763],"iteration":252,"passed_time":3.090433779,"remaining_time":9.124719498},
{"learn":[0.0006265176673],"iteration":253,"passed_time":3.095970231,"remaining_time":9.092888947},
{"learn":[0.0006265181029],"iteration":254,"passed_time":3.136314977,"remaining_time":9.162959443},
{"learn":[0.0006264992338],"iteration":255,"passed_time":3.153319317,"remaining_time":9.164334264},
{"learn":[0.0006264985092],"iteration":256,"passed_time":3.159687331,"remaining_time":9.134815904},
{"learn":[0.0006264867761],"iteration":257,"passed_time":3.174313598,"remaining_time":9.129227479},
{"learn":[0.0006264853001],"iteration":258,"passed_time":3.180707632,"remaining_time":9.100016816},
{"learn":[0.0006264792312],"iteration":259,"passed_time":3.190091479,"remaining_time":9.079491133},
{"learn":[0.0006264828725],"iteration":260,"passed_time":3.200396742,"remaining_time":9.06165974},
{"learn":[0.0006264597263],"iteration":261,"passed_time":3.212818775,"remaining_time":9.049848306},
{"learn":[0.0006264597263],"iteration":262,"passed_time":3.221080973,"remaining_time":9.026375199},
{"learn":[0.0006264705657],"iteration":263,"passed_time":3.225162884,"remaining_time":8.991363191},
{"learn":[0.0006264658797],"iteration":264,"passed_time":3.238213208,"remaining_time":8.981459276},
{"learn":[0.0006264662265],"iteration":265,"passed_time":3.247642523,"remaining_time":8.961539895},
{"learn":[0.0006264701301],"iteration":266,"passed_time":3.258030522,"remaining_time":8.944330983},
{"learn":[0.0006264672669],"iteration":267,"passed_time":3.268370672,"remaining_time":8.927042282},
{"learn":[0.0006264580191],"iteration":268,"passed_time":3.280089453,"remaining_time":8.913551635},
{"learn":[0.0006264346685],"iteration":269,"passed_time":3.29259994,"remaining_time":8.902214651},
{"learn":[0.0006264346107],"iteration":270,"passed_time":3.302580035,"remaining_time":8.884062161},
{"learn":[0.0006264205656],"iteration":271,"passed_time":3.311528501,"remaining_time":8.863208634},
{"learn":[0.0006264283995],"iteration":272,"passed_time":3.320735289,"remaining_time":8.843130239},
{"learn":[0.0006264395236],"iteration":273,"passed_time":3.327376826,"remaining_time":8.816334217},
{"learn":[0.0006264258831],"iteration":274,"passed_time":3.337296459,"remaining_time":8.798327029},
{"learn":[0.0006264110599],"iteration":275,"passed_time":3.349788589,"remaining_time":8.78712659},
{"learn":[0.0006263777947],"iteration":276,"passed_time":3.361158036,"remaining_time":8.772986499},
{"learn":[0.0006263832855],"iteration":277,"passed_time":3.373564353,"remaining_time":8.761559219},
{"learn":[0.0006188453869],"iteration":278,"passed_time":3.384874086,"remaining_time":8.747291096},
{"learn":[0.0006188362547],"iteration":279,"passed_time":3.397655688,"remaining_time":8.736828912},
{"learn":[0.0006188362547],"iteration":280,"passed_time":3.409178202,"remaining_time":8.723128566},
{"learn":[0.000618824437],"iteration":281,"passed_time":3.422671405,"remaining_time":8.714461237},
{"learn":[0.0006188314885],"iteration":282,"passed_time":3.434385515,"remaining_time":8.701252347},
{"learn":[0.0006188331646],"iteration":283,"passed_time":3.449779017,"remaining_time":8.697330197},
{"learn":[0.0006188082534],"iteration":284,"passed_time":3.458584632,"remaining_time":8.676800041},
{"learn":[0.0006188183104],"iteration":285,"passed_time":3.470508973,"remaining_time":8.664137785},
{"learn":[0.0006188183104],"iteration":286,"passed_time":3.480983483,"remaining_time":8.647878827},
{"learn":[0.0006188183104],"iteration":287,"passed_time":3.491597543,"remaining_time":8.632005036},
{"learn":[0.0006188159984],"iteration":288,"passed_time":3.505233763,"remaining_time":8.623602786},
{"learn":[0.0006188090894],"iteration":289,"passed_time":3.516197916,"remaining_time":8.608622483},
{"learn":[0.0006188129929],"iteration":290,"passed_time":3.526748217,"remaining_time":8.592661462},
{"learn":[0.0006187924434],"iteration":291,"passed_time":3.538784131,"remaining_time":8.580339606},
{"learn":[0.0006187981076],"iteration":292,"passed_time":3.551989336,"remaining_time":8.570841161},
{"learn":[0.0006187872147],"iteration":293,"passed_time":3.561488343,"remaining_time":8.552417584},
{"learn":[0.0006187870103],"iteration":294,"passed_time":3.57487932,"remaining_time":8.543355663},
{"learn":[0.0006187898735],"iteration":295,"passed_time":3.580480079,"remaining_time":8.515736404},
{"learn":[0.0006187898735],"iteration":296,"passed_time":3.585881575,"remaining_time":8.487793761},
{"learn":[0.0006187806257],"iteration":297,"passed_time":3.624610621,"remaining_time":8.538512269},
{"learn":[0.0006187794119],"iteration":298,"passed_time":3.634478658,"remaining_time":8.520968358},
{"learn":[0.0006187780826],"iteration":299,"passed_time":3.643984883,"remaining_time":8.502631395},
{"learn":[0.0006187644153],"iteration":300,"passed_time":3.653629675,"remaining_time":8.484674893},
{"learn":[0.0006187712045],"iteration":301,"passed_time":3.666439105,"remaining_time":8.474087732},
{"learn":[0.0006187724183],"iteration":302,"passed_time":3.676168893,"remaining_time":8.45640171},
{"learn":[0.0006187491255],"iteration":303,"passed_time":3.690050286,"remaining_time":8.448273023},
{"learn":[0.0006187700175],"iteration":304,"passed_time":3.698314882,"remaining_time":8.427307683},
{"learn":[0.0006187482274],"iteration":305,"passed_time":3.707594822,"remaining_time":8.408728126},
{"learn":[0.0006187364943],"iteration":306,"passed_time":3.717133942,"remaining_time":8.390794208},
{"learn":[0.0006187536916],"iteration":307,"passed_time":3.723411856,"remaining_time":8.365587677},
{"learn":[0.0006187371879],"iteration":308,"passed_time":3.734165857,"remaining_time":8.350513293},
{"learn":[0.0006187352848],"iteration":309,"passed_time":3.745054768,"remaining_time":8.335767063},
{"learn":[0.0006187269576],"iteration":310,"passed_time":3.75407666,"remaining_time":8.316909386},
{"learn":[0.0006187234629],"iteration":311,"passed_time":3.765368009,"remaining_time":8.303119199},
{"learn":[0.000618725139],"iteration":312,"passed_time":3.775614709,"remaining_time":8.287052093},
{"learn":[0.00061872742],"iteration":313,"passed_time":3.78696882,"remaining_time":8.273441434},
{"learn":[0.0006187054565],"iteration":314,"passed_time":3.798899471,"remaining_time":8.26109885},
{"learn":[0.0006187054565],"iteration":315,"passed_time":3.811593767,"remaining_time":8.250411824},
{"learn":[0.0006187150821],"iteration":316,"passed_time":3.822181665,"remaining_time":8.235173745},
{"learn":[0.0006187072215],"iteration":317,"passed_time":3.833571805,"remaining_time":8.221685444},
{"learn":[0.0006186980583],"iteration":318,"passed_time":3.843216728,"remaining_time":8.204484613},
{"learn":[0.0006186873655],"iteration":319,"passed_time":3.854994847,"remaining_time":8.191864051},
{"learn":[0.0006186906333],"iteration":320,"passed_time":3.868287227,"remaining_time":8.182451797},
{"learn":[0.0006186911802],"iteration":321,"passed_time":3.878518176,"remaining_time":8.166569327},
{"learn":[0.0006186577459],"iteration":322,"passed_time":3.891248295,"remaining_time":8.15596005},
{"learn":[0.0006186735827],"iteration":323,"passed_time":3.895054148,"remaining_time":8.126717914},
{"learn":[0.0006186590041],"iteration":324,"passed_time":3.900834739,"remaining_time":8.101733688},
{"learn":[0.0006186620985],"iteration":325,"passed_time":3.907464187,"remaining_time":8.078622277},
{"learn":[0.0006186503344],"iteration":326,"passed_time":3.911997465,"remaining_time":8.051297535},
{"learn":[0.0006186503344],"iteration":327,"passed_time":3.920749462,"remaining_time":8.032754996},
{"learn":[0.0006186553628],"iteration":328,"passed_time":3.93855958,"remaining_time":8.032746133},
{"learn":[0.0006186512324],"iteration":329,"passed_time":3.946329208,"remaining_time":8.01224415},
{"learn":[0.000618639217],"iteration":330,"passed_time":3.960408235,"remaining_time":8.004571327},
{"learn":[0.0006186512123],"iteration":331,"passed_time":3.972533305,"remaining_time":7.992928457},
{"learn":[0.0006186510657],"iteration":332,"passed_time":3.981676036,"remaining_time":7.975309056},
{"learn":[0.0006116868492],"iteration":333,"passed_time":3.987260239,"remaining_time":7.950644669},
{"learn":[0.0006043658797],"iteration":334,"passed_time":3.9928237,"remaining_time":7.926053016},
{"learn":[0.0006043644037],"iteration":335,"passed_time":3.997836369,"remaining_time":7.900486157},
{"learn":[0.0006043624964],"iteration":336,"passed_time":4.002990323,"remaining_time":7.875319241},
{"learn":[0.0006043533374],"iteration":337,"passed_time":4.057088514,"remaining_time":7.946131941},
{"learn":[0.0006043611402],"iteration":338,"passed_time":4.072505291,"remaining_time":7.940784653},
{"learn":[0.0006043611402],"iteration":339,"passed_time":4.077781338,"remaining_time":7.915693185},
{"learn":[0.0006043499851],"iteration":340,"passed_time":4.083049099,"remaining_time":7.890701925},
{"learn":[0.000604343076],"iteration":341,"passed_time":4.088382228,"remaining_time":7.865951771},
{"learn":[0.0006043383098],"iteration":342,"passed_time":4.115137196,"remaining_time":7.88234734},
{"learn":[0.000604338221],"iteration":343,"passed_time":4.142966407,"remaining_time":7.90054059},
{"learn":[0.0006043294666],"iteration":344,"passed_time":4.154373512,"remaining_time":7.887288841},
{"learn":[0.0006043377586],"iteration":345,"passed_time":4.18945719,"remaining_time":7.918800584},
{"learn":[0.0006043379362],"iteration":346,"passed_time":4.200933081,"remaining_time":7.90550231},
{"learn":[0.0006043111712],"iteration":347,"passed_time":4.229325348,"remaining_time":7.923908411},
{"learn":[0.0006043138299],"iteration":348,"passed_time":4.234308569,"remaining_time":7.898380741},
{"learn":[0.0006043090637],"iteration":349,"passed_time":4.245135416,"remaining_time":7.883822915},
{"learn":[0.0006043086013],"iteration":350,"passed_time":4.258609473,"remaining_time":7.874181049},
{"learn":[0.0006043159107],"iteration":351,"passed_time":4.273859251,"remaining_time":7.867786348},
{"learn":[0.0006042987755],"iteration":352,"passed_time":4.282856396,"remaining_time":7.84988127},
{"learn":[0.000604304351],"iteration":353,"passed_time":4.293042244,"remaining_time":7.834195733},
{"learn":[0.0006042924755],"iteration":354,"passed_time":4.298580877,"remaining_time":7.81009765},
{"learn":[0.0006042908261],"iteration":355,"passed_time":4.314007376,"remaining_time":7.803990872},
{"learn":[0.0006042908261],"iteration":356,"passed_time":4.324191031,"remaining_time":7.788388887},
{"learn":[0.0006042727662],"iteration":357,"passed_time":4.337032514,"remaining_time":7.777583447},
{"learn":[0.0006042777369],"iteration":358,"passed_time":4.351035138,"remaining_time":7.768839898},
{"learn":[0.0006042777369],"iteration":359,"passed_time":4.36610216,"remaining_time":7.761959395},
{"learn":[0.0006042688359],"iteration":360,"passed_time":4.377590616,"remaining_time":7.748699179},
{"learn":[0.0006042711746],"iteration":361,"passed_time":4.391965066,"remaining_time":7.740535117},
{"learn":[0.0006042592103],"iteration":362,"passed_time":4.405093032,"remaining_time":7.730149481},
{"learn":[0.0006042592103],"iteration":363,"passed_time":4.419084035,"remaining_time":7.72125672},
{"learn":[0.0006042592103],"iteration":364,"passed_time":4.433804145,"remaining_time":7.713604471},
{"learn":[0.0006042592103],"iteration":365,"passed_time":4.445736549,"remaining_time":7.701084623},
{"learn":[0.0006042448805],"iteration":366,"passed_time":4.458478389,"remaining_time":7.689964087},
{"learn":[0.0006042476238],"iteration":367,"passed_time":4.474302519,"remaining_time":7.684128239},
{"learn":[0.0006042549064],"iteration":368,"passed_time":4.490434672,"remaining_time":7.678764981},
{"learn":[0.0006042502247],"iteration":369,"passed_time":4.505685193,"remaining_time":7.671842355},
{"learn":[0.0006042501669],"iteration":370,"passed_time":4.513274056,"remaining_time":7.651885124},
{"learn":[0.0006042501669],"iteration":371,"passed_time":4.521735505,"remaining_time":7.633467465},
{"learn":[0.0006042537772],"iteration":372,"passed_time":4.531778605,"remaining_time":7.617761891},
{"learn":[0.0006042305732],"iteration":373,"passed_time":4.543147622,"remaining_time":7.604305913},
{"learn":[0.0006042254601],"iteration":374,"passed_time":4.556821227,"remaining_time":7.594702046},
{"learn":[0.0006042341835],"iteration":375,"passed_time":4.57006735,"remaining_time":7.584367091},
{"learn":[0.0006042272209],"iteration":376,"passed_time":4.57775449,"remaining_time":7.564830363},
{"learn":[0.0006042272209],"iteration":377,"passed_time":4.590534109,"remaining_time":7.553736021},
{"learn":[0.0006042112374],"iteration":378,"passed_time":4.606210535,"remaining_time":7.547379268},
{"learn":[0.0006042112374],"iteration":379,"passed_time":4.618743112,"remaining_time":7.535844025},
{"learn":[0.0006042112374],"iteration":380,"passed_time":4.633274236,"remaining_time":7.52755053},
{"learn":[0.0006042095035],"iteration":381,"passed_time":4.638398781,"remaining_time":7.504006405},
{"learn":[0.0006041958052],"iteration":382,"passed_time":4.643531634,"remaining_time":7.480571849},
{"learn":[0.0006042061244],"iteration":383,"passed_time":4.64864714,"remaining_time":7.457204787},
{"learn":[0.0006041989263],"iteration":384,"passed_time":4.653839176,"remaining_time":7.434054787},
{"learn":[0.0006041919705],"iteration":385,"passed_time":4.658952062,"remaining_time":7.410871933},
{"learn":[0.0006041645204],"iteration":386,"passed_time":4.664205737,"remaining_time":7.38800547},
{"learn":[0.0006041678727],"iteration":387,"passed_time":4.669363209,"remaining_time":7.365078051},
{"learn":[0.0006041738795],"iteration":388,"passed_time":4.67453263,"remaining_time":7.342260763},
{"learn":[0.0005988156902],"iteration":389,"passed_time":4.68006389,"remaining_time":7.32009993},
{"learn":[0.0005988273388],"iteration":390,"passed_time":4.751094363,"remaining_time":7.400042115},
{"learn":[0.0005988273388],"iteration":391,"passed_time":4.756299214,"remaining_time":7.377117149},
{"learn":[0.0005988231773],"iteration":392,"passed_time":4.760652915,"remaining_time":7.352967733},
{"learn":[0.0005988158947],"iteration":393,"passed_time":4.775411439,"remaining_time":7.344922162},
{"learn":[0.0005988200829],"iteration":394,"passed_time":4.788552598,"remaining_time":7.334365372},
{"learn":[0.0005988005202],"iteration":395,"passed_time":4.799328097,"remaining_time":7.3201873},
{"learn":[0.0005988050553],"iteration":396,"passed_time":4.809499748,"remaining_time":7.305109189},
{"learn":[0.0005988050553],"iteration":397,"passed_time":4.821017082,"remaining_time":7.292091164},
{"learn":[0.0005987874845],"iteration":398,"passed_time":4.832556601,"remaining_time":7.279114078},
{"learn":[0.0005987874845],"iteration":399,"passed_time":4.846132413,"remaining_time":7.26919862},
{"learn":[0.0005987817625],"iteration":400,"passed_time":4.858180351,"remaining_time":7.256982619},
{"learn":[0.0005987888717],"iteration":401,"passed_time":4.87108126,"remaining_time":7.246036302},
{"learn":[0.0005987614174],"iteration":402,"passed_time":4.881956177,"remaining_time":7.232079001},
{"learn":[0.0005987710697],"iteration":403,"passed_time":4.893576675,"remaining_time":7.219236877},
{"learn":[0.0005987716209],"iteration":404,"passed_time":4.907008182,"remaining_time":7.209061404},
{"learn":[0.0005987788458],"iteration":405,"passed_time":4.921787446,"remaining_time":7.200841731},
{"learn":[0.0005987628556],"iteration":406,"passed_time":4.936233841,"remaining_time":7.192104835},
{"learn":[0.0005987413813],"iteration":407,"passed_time":4.950697738,"remaining_time":7.183365346},
{"learn":[0.0005987606592],"iteration":408,"passed_time":4.964078356,"remaining_time":7.17303254},
{"learn":[0.0005987606592],"iteration":409,"passed_time":4.97606936,"remaining_time":7.160685177},
{"learn":[0.0005987441288],"iteration":410,"passed_time":4.988936701,"remaining_time":7.149595418},
{"learn":[0.0005987441288],"iteration":411,"passed_time":5.003066744,"remaining_time":7.14029914},
{"learn":[0.0005987429996],"iteration":412,"passed_time":5.009527291,"remaining_time":7.12007874},
{"learn":[0.0005987497043],"iteration":413,"passed_time":5.017616836,"remaining_time":7.102230595},
{"learn":[0.0005987511803],"iteration":414,"passed_time":5.02850579,"remaining_time":7.088375632},
{"learn":[0.0005987410612],"iteration":415,"passed_time":5.040873046,"remaining_time":7.076610237},
{"learn":[0.0005987410612],"iteration":416,"passed_time":5.046985772,"remaining_time":7.056097614},
{"learn":[0.0005987313554],"iteration":417,"passed_time":5.060934797,"remaining_time":7.046564717},
{"learn":[0.0005987238683],"iteration":418,"passed_time":5.071731839,"remaining_time":7.032640092},
{"learn":[0.0005987238683],"iteration":419,"passed_time":5.083843754,"remaining_time":7.020546137},
{"learn":[0.0005987238683],"iteration":420,"passed_time":5.093029189,"remaining_time":7.004427316},
{"learn":[0.0005987252865],"iteration":421,"passed_time":5.107616577,"remaining_time":6.995740241},
{"learn":[0.0005987252865],"iteration":422,"passed_time":5.118469152,"remaining_time":6.981930735},
{"learn":[0.0005987154297],"iteration":423,"passed_time":5.130809385,"remaining_time":6.970156145},
{"learn":[0.0005987134068],"iteration":424,"passed_time":5.141409552,"remaining_time":6.956024688},
{"learn":[0.0005987136069],"iteration":425,"passed_time":5.153780355,"remaining_time":6.944295595},
{"learn":[0.0005987055461],"iteration":426,"passed_time":5.161252557,"remaining_time":6.925989965},
{"learn":[0.0005986916745],"iteration":427,"passed_time":5.176914135,"remaining_time":6.918679638},
{"learn":[0.0005986919635],"iteration":428,"passed_time":5.1932547,"remaining_time":6.912234111},
{"learn":[0.00059867951],"iteration":429,"passed_time":5.19858451,"remaining_time":6.891146908},
{"learn":[0.0005986751441],"iteration":430,"passed_time":5.203478111,"remaining_time":6.869556949},
{"learn":[0.0005986751441],"iteration":431,"passed_time":5.225908535,"remaining_time":6.871101962},
{"learn":[0.000598678901],"iteration":432,"passed_time":5.231114047,"remaining_time":6.84998075},
{"learn":[0.0005986751173],"iteration":433,"passed_time":5.244351243,"remaining_time":6.839407382},
{"learn":[0.0005986741925],"iteration":434,"passed_time":5.259292476,"remaining_time":6.831035055},
{"learn":[0.0005986676303],"iteration":435,"passed_time":5.277777649,"remaining_time":6.827216959},
{"learn":[0.0005986647981],"iteration":436,"passed_time":5.296956268,"remaining_time":6.824225124},
{"learn":[0.0005986525448],"iteration":437,"passed_time":5.313116245,"remaining_time":6.817286141},
{"learn":[0.0005986657807],"iteration":438,"passed_time":5.328118048,"remaining_time":6.808825114},
{"learn":[0.000598647054],"iteration":439,"passed_time":5.342761151,"remaining_time":6.799877829},
{"learn":[0.0005986499749],"iteration":440,"passed_time":5.353473632,"remaining_time":6.785922359},
{"learn":[0.0005986506953],"iteration":441,"passed_time":5.367890563,"remaining_time":6.776658222},
{"learn":[0.0005986429813],"iteration":442,"passed_time":5.378723351,"remaining_time":6.762864349},
{"learn":[0.0005986429813],"iteration":443,"passed_time":5.39342491,"remaining_time":6.753928491},
{"learn":[0.0005986489035],"iteration":444,"passed_time":5.406499354,"remaining_time":6.742937397},
{"learn":[0.0005986305503],"iteration":445,"passed_time":5.419830538,"remaining_time":6.73225587},
{"learn":[0.0005986364768],"iteration":446,"passed_time":5.430499246,"remaining_time":6.718268642},
{"learn":[0.0005986415363],"iteration":447,"passed_time":5.44280781,"remaining_time":6.706316765},
{"learn":[0.0005986335291],"iteration":448,"passed_time":5.454874541,"remaining_time":6.69406653},
{"learn":[0.0005986268555],"iteration":449,"passed_time":5.466387175,"remaining_time":6.68113988},
{"learn":[0.0005986268555],"iteration":450,"passed_time":5.471438643,"remaining_time":6.660354357},
{"learn":[0.0005986271134],"iteration":451,"passed_time":5.476655977,"remaining_time":6.639839548},
{"learn":[0.000598620062],"iteration":452,"passed_time":5.481694328,"remaining_time":6.619176153},
{"learn":[0.0005986283272],"iteration":453,"passed_time":5.486549874,"remaining_time":6.598361743},
{"learn":[0.0005986063948],"iteration":454,"passed_time":5.491794695,"remaining_time":6.578083756},
{"learn":[0.000598603096],"iteration":455,"passed_time":5.497190769,"remaining_time":6.558052145},
{"learn":[0.0005986005571],"iteration":456,"passed_time":5.502502946,"remaining_time":6.537984901},
{"learn":[0.0005986063948],"iteration":457,"passed_time":5.507751859,"remaining_time":6.517907221},
{"learn":[0.0005985896021],"iteration":458,"passed_time":5.513158899,"remaining_time":6.498080533},
{"learn":[0.0005985895754],"iteration":459,"passed_time":5.561456914,"remaining_time":6.528666812},
{"learn":[0.0005985982719],"iteration":460,"passed_time":5.577176593,"remaining_time":6.520820355},
{"learn":[0.0005985826973],"iteration":461,"passed_time":5.589220022,"remaining_time":6.508658813},
{"learn":[0.0005985746633],"iteration":462,"passed_time":5.598801453,"remaining_time":6.49364229},
{"learn":[0.0005985755881],"iteration":463,"passed_time":5.61188041,"remaining_time":6.482689439},
{"learn":[0.0005985724938],"iteration":464,"passed_time":5.617153905,"remaining_time":6.462746966},
{"learn":[0.0005985597513],"iteration":465,"passed_time":5.625835424,"remaining_time":6.446772783},
{"learn":[0.0005985722893],"iteration":466,"passed_time":5.639466252,"remaining_time":6.436478613},
{"learn":[0.0005957856443],"iteration":467,"passed_time":5.65125497,"remaining_time":6.424076162},
{"learn":[0.0005957959592],"iteration":468,"passed_time":5.664058657,"remaining_time":6.412825473},
{"learn":[0.0005957933893],"iteration":469,"passed_time":5.676103943,"remaining_time":6.400712957},
{"learn":[0.0005957660973],"iteration":470,"passed_time":5.694290022,"remaining_time":6.39549771},
{"learn":[0.0005957660973],"iteration":471,"passed_time":5.71536617,"remaining_time":6.393460461},
{"learn":[0.0005957632962],"iteration":472,"passed_time":5.732615501,"remaining_time":6.387079004},
{"learn":[0.0005957632962],"iteration":473,"passed_time":5.742465894,"remaining_time":6.372441055},
{"learn":[0.0005957647412],"iteration":474,"passed_time":5.760011584,"remaining_time":6.366328593},
{"learn":[0.000595755031],"iteration":475,"passed_time":5.775399883,"remaining_time":6.357793148},
{"learn":[0.0005957604909],"iteration":476,"passed_time":5.791887608,"remaining_time":6.350434421},
{"learn":[0.0005957560982],"iteration":477,"passed_time":5.805560859,"remaining_time":6.33996395},
{"learn":[0.0005957474862],"iteration":478,"passed_time":5.819089018,"remaining_time":6.329322293},
{"learn":[0.0005957461568],"iteration":479,"passed_time":5.830461809,"remaining_time":6.316333627},
{"learn":[0.0005957445117],"iteration":480,"passed_time":5.843604581,"remaining_time":6.305261492},
{"learn":[0.0005957376914],"iteration":481,"passed_time":5.856357676,"remaining_time":6.293761984},
{"learn":[0.000595738385],"iteration":482,"passed_time":5.86969213,"remaining_time":6.282879568},
{"learn":[0.000595738385],"iteration":483,"passed_time":5.877514889,"remaining_time":6.266110915},
{"learn":[0.0005957187603],"iteration":484,"passed_time":5.891232089,"remaining_time":6.255638198},
{"learn":[0.0005957236464],"iteration":485,"passed_time":5.903316169,"remaining_time":6.243424919},
{"learn":[0.0005957309868],"iteration":486,"passed_time":5.914474264,"remaining_time":6.230236751},
{"learn":[0.0005957151768],"iteration":487,"passed_time":5.925250462,"remaining_time":6.216656223},
{"learn":[0.0005957120289],"iteration":488,"passed_time":5.939090861,"remaining_time":6.206289223},
{"learn":[0.0005957120289],"iteration":489,"passed_time":5.952518682,"remaining_time":6.195478628},
{"learn":[0.0005957096013],"iteration":490,"passed_time":5.962979861,"remaining_time":6.181581974},
{"learn":[0.000595711362],"iteration":491,"passed_time":5.973498311,"remaining_time":6.167758419},
{"learn":[0.0005957007849],"iteration":492,"passed_time":5.989068995,"remaining_time":6.159143977},
{"learn":[0.0005957007849],"iteration":493,"passed_time":6.001407389,"remaining_time":6.147190564},
{"learn":[0.0005956913637],"iteration":494,"passed_time":6.01169045,"remaining_time":6.133138741},
{"learn":[0.0005956860463],"iteration":495,"passed_time":6.027956026,"remaining_time":6.125181124},
{"learn":[0.0005956792838],"iteration":496,"passed_time":6.033452623,"remaining_time":6.106291086},
{"learn":[0.0005956755001],"iteration":497,"passed_time":6.045546691,"remaining_time":6.094105299},
{"learn":[0.0005956876646],"iteration":498,"passed_time":6.062095125,"remaining_time":6.086392099},
{"learn":[0.0005956805554],"iteration":499,"passed_time":6.072013319,"remaining_time":6.072013319},
{"learn":[0.0005956805554],"iteration":500,"passed_time":6.082160971,"remaining_time":6.057880887},
{"learn":[0.0005956854105],"iteration":501,"passed_time":6.094763441,"remaining_time":6.046199589},
{"learn":[0.0005956854105],"iteration":502,"passed_time":6.108303307,"remaining_time":6.035440843},
{"learn":[0.0005956697471],"iteration":503,"passed_time":6.117399162,"remaining_time":6.020297588},
{"learn":[0.0005956666259],"iteration":504,"passed_time":6.127088947,"remaining_time":6.005760453},
{"learn":[0.0005956666259],"iteration":505,"passed_time":6.146323101,"remaining_time":6.000560498},
{"learn":[0.0005956666259],"iteration":506,"passed_time":6.158995687,"remaining_time":5.988924801},
{"learn":[0.0005956722056],"iteration":507,"passed_time":6.171764444,"remaining_time":5.977378162},
{"learn":[0.0005956604993],"iteration":508,"passed_time":6.185475466,"remaining_time":5.966735666},
{"learn":[0.0005956597789],"iteration":509,"passed_time":6.199841205,"remaining_time":5.956710177},
{"learn":[0.0005956599213],"iteration":510,"passed_time":6.21266234,"remaining_time":5.945189598},
{"learn":[0.0005956432753],"iteration":511,"passed_time":6.224747541,"remaining_time":5.9329625},
{"learn":[0.0005956479035],"iteration":512,"passed_time":6.237913678,"remaining_time":5.921762107},
{"learn":[0.0005956481304],"iteration":513,"passed_time":6.249899502,"remaining_time":5.90943805},
{"learn":[0.0005956499799],"iteration":514,"passed_time":6.257383612,"remaining_time":5.892875829},
{"learn":[0.0005956458805],"iteration":515,"passed_time":6.267338659,"remaining_time":5.878666494},
{"learn":[0.0005956445201],"iteration":516,"passed_time":6.277930767,"remaining_time":5.865068782},
{"learn":[0.0005956445201],"iteration":517,"passed_time":6.288873261,"remaining_time":5.85180871},
{"learn":[0.0005956416034],"iteration":518,"passed_time":6.301411026,"remaining_time":5.840036038},
{"learn":[0.0005956321512],"iteration":519,"passed_time":6.312377166,"remaining_time":5.826809691},
{"learn":[0.0005956321512],"iteration":520,"passed_time":6.321721343,"remaining_time":5.812100813},
{"learn":[0.0005956334495],"iteration":521,"passed_time":6.33225807,"remaining_time":5.798504516},
{"learn":[0.0005956280475],"iteration":522,"passed_time":6.345537912,"remaining_time":5.787421767},
{"learn":[0.0005956362817],"iteration":523,"passed_time":6.355632685,"remaining_time":5.773437324},
{"learn":[0.0005956076824],"iteration":524,"passed_time":6.369145665,"remaining_time":5.762560364},
{"learn":[0.0005956113237],"iteration":525,"passed_time":6.384199597,"remaining_time":5.753061994},
{"learn":[0.0005956113237],"iteration":526,"passed_time":6.396378494,"remaining_time":5.740962102},
{"learn":[0.0005956011779],"iteration":527,"passed_time":6.40942591,"remaining_time":5.729638314},
{"learn":[0.0005956011779],"iteration":528,"passed_time":6.418647296,"remaining_time":5.714901468},
{"learn":[0.0005956090385],"iteration":529,"passed_time":6.430796785,"remaining_time":5.702782055},
{"learn":[0.0005956100789],"iteration":530,"passed_time":6.443639668,"remaining_time":5.691274961},
{"learn":[0.0005955912098],"iteration":531,"passed_time":6.454767184,"remaining_time":5.678253838},
{"learn":[0.0005955912098],"iteration":532,"passed_time":6.467630289,"remaining_time":5.666760497},
{"learn":[0.0005955888978],"iteration":533,"passed_time":6.476838657,"remaining_time":5.652072686},
{"learn":[0.0005955888978],"iteration":534,"passed_time":6.487259715,"remaining_time":5.638459378},
{"learn":[0.0005955826823],"iteration":535,"passed_time":6.500132901,"remaining_time":5.62698072},
{"learn":[0.0005955920767],"iteration":536,"passed_time":6.512655156,"remaining_time":5.615194296},
{"learn":[0.0005955824511],"iteration":537,"passed_time":6.525189203,"remaining_time":5.603415264},
{"learn":[0.0005955824511],"iteration":538,"passed_time":6.536831893,"remaining_time":5.590871063},
{"learn":[0.0005955824511],"iteration":539,"passed_time":6.550359103,"remaining_time":5.579935533},
{"learn":[0.0005955824511],"iteration":540,"passed_time":6.562085337,"remaining_time":5.567462421},
{"learn":[0.0005955873373],"iteration":541,"passed_time":6.575198008,"remaining_time":5.556163631},
{"learn":[0.0005955859191],"iteration":542,"passed_time":6.588223681,"remaining_time":5.54478494},
{"learn":[0.0005955859191],"iteration":543,"passed_time":6.602823262,"remaining_time":5.534719499},
{"learn":[0.0005955813262],"iteration":544,"passed_time":6.610571882,"remaining_time":5.51891781},
{"learn":[0.0005955779161],"iteration":545,"passed_time":6.622109969,"remaining_time":5.506296568},
{"learn":[0.0005955779161],"iteration":546,"passed_time":6.633717921,"remaining_time":5.493737145},
{"learn":[0.000595580486],"iteration":547,"passed_time":6.644642867,"remaining_time":5.48061784},
{"learn":[0.0005955587915],"iteration":548,"passed_time":6.657265401,"remaining_time":5.468901086},
{"learn":[0.0005955587915],"iteration":549,"passed_time":6.669061085,"remaining_time":5.456504524},
{"learn":[0.000595555817],"iteration":550,"passed_time":6.681421456,"remaining_time":5.444570298},
{"learn":[0.0005955286784],"iteration":551,"passed_time":6.693609136,"remaining_time":5.432494371},
{"learn":[0.0005955363389],"iteration":552,"passed_time":6.703901277,"remaining_time":5.418885843},
{"learn":[0.0005955198663],"iteration":553,"passed_time":6.717846614,"remaining_time":5.408230307},
{"learn":[0.0005955239389],"iteration":554,"passed_time":6.733774512,"remaining_time":5.399152536},
{"learn":[0.0005955091735],"iteration":555,"passed_time":6.743313093,"remaining_time":5.384947866},
{"learn":[0.0005955146911],"iteration":556,"passed_time":6.755642433,"remaining_time":5.37297953},
{"learn":[0.0005955226096],"iteration":557,"passed_time":6.769108099,"remaining_time":5.36191},
{"learn":[0.0005954977872],"iteration":558,"passed_time":6.783099783,"remaining_time":5.351246877},
{"learn":[0.0005955181591],"iteration":559,"passed_time":6.798102426,"remaining_time":5.341366192},
{"learn":[0.000595494924],"iteration":560,"passed_time":6.81091458,"remaining_time":5.329753121},
{"learn":[0.000595513913],"iteration":561,"passed_time":6.8206691,"remaining_time":5.315752786},
{"learn":[0.0005954988543],"iteration":562,"passed_time":6.845720096,"remaining_time":5.313640643},
{"learn":[0.0005954875568],"iteration":563,"passed_time":6.858917884,"remaining_time":5.302284038},
{"learn":[0.0005954867209],"iteration":564,"passed_time":6.86839968,"remaining_time":5.288059931},
{"learn":[0.0005954873256],"iteration":565,"passed_time":6.873520101,"remaining_time":5.270508346},
{"learn":[0.000595478567],"iteration":566,"passed_time":6.923735362,"remaining_time":5.287438116},
{"learn":[0.000595478567],"iteration":567,"passed_time":6.93764104,"remaining_time":5.276515721},
{"learn":[0.0005954811412],"iteration":568,"passed_time":6.949669951,"remaining_time":5.264161246},
{"learn":[0.0005954846091],"iteration":569,"passed_time":6.978334337,"remaining_time":5.264357483},
{"learn":[0.0005954677209],"iteration":570,"passed_time":6.989342354,"remaining_time":5.251187163},
{"learn":[0.000595475239],"iteration":571,"passed_time":7.004699037,"remaining_time":5.2412783},
{"learn":[0.0005954547162],"iteration":572,"passed_time":7.022516457,"remaining_time":5.233184166},
{"learn":[0.0005954611361],"iteration":573,"passed_time":7.027812958,"remaining_time":5.215763624},
{"learn":[0.0005954551518],"iteration":574,"passed_time":7.033107691,"remaining_time":5.198383945},
{"learn":[0.0005954282445],"iteration":575,"passed_time":7.06955523,"remaining_time":5.203978156},
{"learn":[0.0005954317434],"iteration":576,"passed_time":7.082855672,"remaining_time":5.192457451},
{"learn":[0.0005954300362],"iteration":577,"passed_time":7.095785711,"remaining_time":5.180660156},
{"learn":[0.0005954361051],"iteration":578,"passed_time":7.108452786,"remaining_time":5.168667742},
{"learn":[0.0005954165691],"iteration":579,"passed_time":7.123047949,"remaining_time":5.158069205},
{"learn":[0.0005954076347],"iteration":580,"passed_time":7.135863615,"remaining_time":5.146173588},
{"learn":[0.0005954170826],"iteration":581,"passed_time":7.152931768,"remaining_time":5.137329002},
{"learn":[0.0005954102313],"iteration":582,"passed_time":7.169180092,"remaining_time":5.127869809},
{"learn":[0.000595392256],"iteration":583,"passed_time":7.185823352,"remaining_time":5.118668689},
{"learn":[0.0005953951459],"iteration":584,"passed_time":7.202885117,"remaining_time":5.109739014},
{"learn":[0.0005953911578],"iteration":585,"passed_time":7.213504899,"remaining_time":5.096230424},
{"learn":[0.000595397689],"iteration":586,"passed_time":7.226975597,"remaining_time":5.084737515},
{"learn":[0.0005954022284],"iteration":587,"passed_time":7.23850749,"remaining_time":5.071879398},
{"learn":[0.0005953840796],"iteration":588,"passed_time":7.256581232,"remaining_time":5.063590639},
{"learn":[0.0005953826036],"iteration":589,"passed_time":7.270622065,"remaining_time":5.052466181},
{"learn":[0.0005953782109],"iteration":590,"passed_time":7.286401489,"remaining_time":5.042535041},
{"learn":[0.0005953604667],"iteration":591,"passed_time":7.299660276,"remaining_time":5.030846947},
{"learn":[0.0005953736759],"iteration":592,"passed_time":7.316972548,"remaining_time":5.021935627},
{"learn":[0.0005953701191],"iteration":593,"passed_time":7.32918126,"remaining_time":5.00950773},
{"learn":[0.0005953636189],"iteration":594,"passed_time":7.344335225,"remaining_time":4.999085321},
{"learn":[0.0005953560162],"iteration":595,"passed_time":7.354798455,"remaining_time":4.985467409},
{"learn":[0.0005953600621],"iteration":596,"passed_time":7.36737723,"remaining_time":4.973288147},
{"learn":[0.0005953356711],"iteration":597,"passed_time":7.382050907,"remaining_time":4.962515827},
{"learn":[0.000595333706],"iteration":598,"passed_time":7.397594788,"remaining_time":4.952313038},
{"learn":[0.000595333706],"iteration":599,"passed_time":7.40908305,"remaining_time":4.9393887},
{"learn":[0.000595319114],"iteration":600,"passed_time":7.42209992,"remaining_time":4.927483973},
{"learn":[0.0005953172644],"iteration":601,"passed_time":7.434702139,"remaining_time":4.915301414},
{"learn":[0.0005953177335],"iteration":602,"passed_time":7.447371142,"remaining_time":4.903161432},
{"learn":[0.0005953177335],"iteration":603,"passed_time":7.457295818,"remaining_time":4.889220437},
{"learn":[0.000595309037],"iteration":604,"passed_time":7.463262563,"remaining_time":4.872708616},
{"learn":[0.0005953190051],"iteration":605,"passed_time":7.469873067,"remaining_time":4.856650146},
{"learn":[0.0005953112644],"iteration":606,"passed_time":7.47755009,"remaining_time":4.84131332},
{"learn":[0.0005953007986],"iteration":607,"passed_time":7.4843846,"remaining_time":4.825458492},
{"learn":[0.0005952923022],"iteration":608,"passed_time":7.496057902,"remaining_time":4.812739967},
{"learn":[0.0005952873047],"iteration":609,"passed_time":7.501444892,"remaining_time":4.796005751},
{"learn":[0.0005952873047],"iteration":610,"passed_time":7.522335262,"remaining_time":4.789179078},
{"learn":[0.0005952904836],"iteration":611,"passed_time":7.537455951,"remaining_time":4.778648544},
{"learn":[0.0005952847726],"iteration":612,"passed_time":7.546857249,"remaining_time":4.76449226},
{"learn":[0.0005952734398],"iteration":613,"passed_time":7.557945373,"remaining_time":4.751411912},
{"learn":[0.0005952734398],"iteration":614,"passed_time":7.568153908,"remaining_time":4.737787406},
{"learn":[0.0005952695983],"iteration":615,"passed_time":7.577792713,"remaining_time":4.723818834},
{"learn":[0.0005952676332],"iteration":616,"passed_time":7.585962323,"remaining_time":4.708952301},
{"learn":[0.0005952676332],"iteration":617,"passed_time":7.591442747,"remaining_time":4.692445193},
{"learn":[0.0005952638184],"iteration":618,"passed_time":7.596142688,"remaining_time":4.675493319},
{"learn":[0.0005952717058],"iteration":619,"passed_time":7.605380917,"remaining_time":4.661362498},
{"learn":[0.0005952518231],"iteration":620,"passed_time":7.614359016,"remaining_time":4.647088675},
{"learn":[0.0005952563046],"iteration":621,"passed_time":7.625997535,"remaining_time":4.634448663},
{"learn":[0.0005952480972],"iteration":622,"passed_time":7.635926895,"remaining_time":4.620777591},
{"learn":[0.0005952520275],"iteration":623,"passed_time":7.648208984,"remaining_time":4.608536183},
{"learn":[0.0005952440513],"iteration":624,"passed_time":7.66188631,"remaining_time":4.597131786},
{"learn":[0.0005952440513],"iteration":625,"passed_time":7.676917147,"remaining_time":4.586528775},
{"learn":[0.0005952586433],"iteration":626,"passed_time":7.691748945,"remaining_time":4.575793232},
{"learn":[0.0005952443403],"iteration":627,"passed_time":7.703027222,"remaining_time":4.562939692},
{"learn":[0.0005952428065],"iteration":628,"passed_time":7.715229151,"remaining_time":4.550635954},
{"learn":[0.0005952346569],"iteration":629,"passed_time":7.725524451,"remaining_time":4.537212773},
{"learn":[0.0005952318248],"iteration":630,"passed_time":7.733554075,"remaining_time":4.52247457},
{"learn":[0.0005952170283],"iteration":631,"passed_time":7.739586883,"remaining_time":4.506594894},
{"learn":[0.0005952238486],"iteration":632,"passed_time":7.756352025,"remaining_time":4.49696871},
{"learn":[0.0005952238486],"iteration":633,"passed_time":7.767120763,"remaining_time":4.483858359},
{"learn":[0.0005952200339],"iteration":634,"passed_time":7.77702583,"remaining_time":4.470258942},
{"learn":[0.0005952086786],"iteration":635,"passed_time":7.787920649,"remaining_time":4.457237604},
{"learn":[0.0005951985328],"iteration":636,"passed_time":7.807321519,"remaining_time":4.449070191},
{"learn":[0.0005951970033],"iteration":637,"passed_time":7.816977297,"remaining_time":4.435338215},
{"learn":[0.0005951966832],"iteration":638,"passed_time":7.839832471,"remaining_time":4.429075934},
{"learn":[0.0005951936509],"iteration":639,"passed_time":7.853076528,"remaining_time":4.417355547},
{"learn":[0.0005951902986],"iteration":640,"passed_time":7.866597349,"remaining_time":4.405785411},
{"learn":[0.0005951817712],"iteration":641,"passed_time":7.878956546,"remaining_time":4.393561439},
{"learn":[0.0005951805307],"iteration":642,"passed_time":7.896573203,"remaining_time":4.38425604},
{"learn":[0.0005951690287],"iteration":643,"passed_time":7.907945905,"remaining_time":4.371473202},
{"learn":[0.0005951690287],"iteration":644,"passed_time":7.91990258,"remaining_time":4.359016149},
{"learn":[0.0005951702115],"iteration":645,"passed_time":7.936070471,"remaining_time":4.348868339},
{"learn":[0.0005951571222],"iteration":646,"passed_time":7.950344677,"remaining_time":4.337668734},
{"learn":[0.0005951571222],"iteration":647,"passed_time":7.962979683,"remaining_time":4.325569211},
{"learn":[0.0005951694023],"iteration":648,"passed_time":7.968321494,"remaining_time":4.309523643},
{"learn":[0.0005951700959],"iteration":649,"passed_time":7.978402701,"remaining_time":4.296062993},
{"learn":[0.0005951657032],"iteration":650,"passed_time":7.9928734,"remaining_time":4.284965924},
{"learn":[0.0005951527295],"iteration":651,"passed_time":8.005316606,"remaining_time":4.272776348},
{"learn":[0.0005951442021],"iteration":652,"passed_time":8.011209779,"remaining_time":4.25710535},
{"learn":[0.0005951472965],"iteration":653,"passed_time":8.022163786,"remaining_time":4.244141697},
{"learn":[0.0005951433662],"iteration":654,"passed_time":8.038557463,"remaining_time":4.234049351},
{"learn":[0.0005951474121],"iteration":655,"passed_time":8.057083412,"remaining_time":4.225055935},
{"learn":[0.0005951427194],"iteration":656,"passed_time":8.092326829,"remaining_time":4.224761191},
{"learn":[0.0005951371129],"iteration":657,"passed_time":8.104563847,"remaining_time":4.212402486},
{"learn":[0.0005951215651],"iteration":658,"passed_time":8.113984356,"remaining_time":4.198586746},
{"learn":[0.0005951135311],"iteration":659,"passed_time":8.126239143,"remaining_time":4.186244407},
{"learn":[0.0005951132999],"iteration":660,"passed_time":8.140312875,"remaining_time":4.174835196},
{"learn":[0.0005951031006],"iteration":661,"passed_time":8.168330695,"remaining_time":4.170537424},
{"learn":[0.0005950966849],"iteration":662,"passed_time":8.173320331,"remaining_time":4.154462973},
{"learn":[0.0005950927814],"iteration":663,"passed_time":8.178396246,"remaining_time":4.13846557},
{"learn":[0.0005950813373],"iteration":664,"passed_time":8.18343919,"remaining_time":4.122484404},
{"learn":[0.0005950979833],"iteration":665,"passed_time":8.188439796,"remaining_time":4.106514853},
{"learn":[0.0005950777537],"iteration":666,"passed_time":8.228232889,"remaining_time":4.107948354},
{"learn":[0.0005950816263],"iteration":667,"passed_time":8.237880521,"remaining_time":4.094275948},
{"learn":[0.0005950875527],"iteration":668,"passed_time":8.289811505,"remaining_time":4.101536036},
{"learn":[0.000595085472],"iteration":669,"passed_time":8.302418253,"remaining_time":4.089250781},
{"learn":[0.0005950835336],"iteration":670,"passed_time":8.322047932,"remaining_time":4.080408002},
{"learn":[0.0005950707601],"iteration":671,"passed_time":8.329821925,"remaining_time":4.065746416},
{"learn":[0.0005950705022],"iteration":672,"passed_time":8.334846585,"remaining_time":4.04976944},
{"learn":[0.0005950731299],"iteration":673,"passed_time":8.339923462,"remaining_time":4.03385022},
{"learn":[0.0005950701821],"iteration":674,"passed_time":8.345068422,"remaining_time":4.017995907},
{"learn":[0.0005950471515],"iteration":675,"passed_time":8.35019434,"remaining_time":4.002164151},
{"learn":[0.0005950412828],"iteration":676,"passed_time":8.355417443,"remaining_time":3.98641039},
{"learn":[0.0005950450975],"iteration":677,"passed_time":8.360724556,"remaining_time":3.970727591},
{"learn":[0.0005950381617],"iteration":678,"passed_time":8.403334281,"remaining_time":3.972710315},
{"learn":[0.0005950255038],"iteration":679,"passed_time":8.418355555,"remaining_time":3.961579085},
{"learn":[0.000595035565],"iteration":680,"passed_time":8.430936837,"remaining_time":3.949293467},
{"learn":[0.000595035565],"iteration":681,"passed_time":8.441726291,"remaining_time":3.936171497},
{"learn":[0.0005950301277],"iteration":682,"passed_time":8.451713886,"remaining_time":3.92268419},
{"learn":[0.0005950213423],"iteration":683,"passed_time":8.459165194,"remaining_time":3.908035382},
{"learn":[0.0005950211422],"iteration":684,"passed_time":8.466664224,"remaining_time":3.893429534},
{"learn":[0.0005950034247],"iteration":685,"passed_time":8.47985162,"remaining_time":3.881448117},
{"learn":[0.0005950023175],"iteration":686,"passed_time":8.487481771,"remaining_time":3.866931287},
{"learn":[0.0005949963911],"iteration":687,"passed_time":8.510236081,"remaining_time":3.859293106},
{"learn":[0.0005950027799],"iteration":688,"passed_time":8.524506457,"remaining_time":3.847781579},
{"learn":[0.0005949941369],"iteration":689,"passed_time":8.533883868,"remaining_time":3.834063767},
{"learn":[0.0005949861339],"iteration":690,"passed_time":8.5519625,"remaining_time":3.824249512},
{"learn":[0.0005949930965],"iteration":691,"passed_time":8.566230343,"remaining_time":3.812715239},
{"learn":[0.0005949784157],"iteration":692,"passed_time":8.579990789,"remaining_time":3.800948301},
{"learn":[0.0005949784157],"iteration":693,"passed_time":8.592807616,"remaining_time":3.788759554},
{"learn":[0.0005949643128],"iteration":694,"passed_time":8.605639503,"remaining_time":3.776575609},
{"learn":[0.0005949638815],"iteration":695,"passed_time":8.617122409,"remaining_time":3.763800592},
{"learn":[0.00059495972],"iteration":696,"passed_time":8.626588956,"remaining_time":3.750152731},
{"learn":[0.0005949765661],"iteration":697,"passed_time":8.636328249,"remaining_time":3.736634858},
{"learn":[0.000594963966],"iteration":698,"passed_time":8.648133985,"remaining_time":3.724017639},
{"learn":[0.000594960298],"iteration":699,"passed_time":8.65806717,"remaining_time":3.710600216},
{"learn":[0.000594960298],"iteration":700,"passed_time":8.669122447,"remaining_time":3.697671343},
{"learn":[0.0005949687055],"iteration":701,"passed_time":8.678642569,"remaining_time":3.684096133},
{"learn":[0.0005949447191],"iteration":702,"passed_time":8.691643286,"remaining_time":3.672002925},
{"learn":[0.0005949567412],"iteration":703,"passed_time":8.700957126,"remaining_time":3.658356973},
{"learn":[0.0005949526375],"iteration":704,"passed_time":8.713941979,"remaining_time":3.64625941},
{"learn":[0.0005949426962],"iteration":705,"passed_time":8.723572399,"remaining_time":3.632762444},
{"learn":[0.0005949469465],"iteration":706,"passed_time":8.732958214,"remaining_time":3.619175045},
{"learn":[0.0005949476668],"iteration":707,"passed_time":8.742959445,"remaining_time":3.60585333},
{"learn":[0.0005949331016],"iteration":708,"passed_time":8.752702575,"remaining_time":3.592435048},
{"learn":[0.0005949119783],"iteration":709,"passed_time":8.761200292,"remaining_time":3.578518429},
{"learn":[0.0005949172112],"iteration":710,"passed_time":8.777494223,"remaining_time":3.567785978},
{"learn":[0.0005949087416],"iteration":711,"passed_time":8.790065577,"remaining_time":3.555532144},
{"learn":[0.0005948819809],"iteration":712,"passed_time":8.802017122,"remaining_time":3.54302793},
{"learn":[0.0005948761122],"iteration":713,"passed_time":8.813696286,"remaining_time":3.53041616},
{"learn":[0.0005948795801],"iteration":714,"passed_time":8.823373098,"remaining_time":3.517008857},
{"learn":[0.0005948770369],"iteration":715,"passed_time":8.834713637,"remaining_time":3.50427189},
{"learn":[0.0005948736268],"iteration":716,"passed_time":8.849817244,"remaining_time":3.4930241},
{"learn":[0.000594872991],"iteration":717,"passed_time":8.866451754,"remaining_time":3.482366845},
{"learn":[0.0005948702167],"iteration":718,"passed_time":8.877206466,"remaining_time":3.469395017},
{"learn":[0.0005948529927],"iteration":719,"passed_time":8.884087165,"remaining_time":3.454922786},
{"learn":[0.0005948617781],"iteration":720,"passed_time":8.893830632,"remaining_time":3.441579398},
{"learn":[0.0005948657662],"iteration":721,"passed_time":8.90074074,"remaining_time":3.427155022},
{"learn":[0.0005948511432],"iteration":722,"passed_time":8.910188028,"remaining_time":3.413723491},
{"learn":[0.0005948577365],"iteration":723,"passed_time":8.921063926,"remaining_time":3.400847574},
{"learn":[0.0005948565184],"iteration":724,"passed_time":8.928324456,"remaining_time":3.386605828},
{"learn":[0.0005948565184],"iteration":725,"passed_time":8.934725144,"remaining_time":3.372058801},
{"learn":[0.000594848022],"iteration":726,"passed_time":8.949762517,"remaining_time":3.360777396},
{"learn":[0.0005948302201],"iteration":727,"passed_time":8.964270801,"remaining_time":3.349287992},
{"learn":[0.0005948302201],"iteration":728,"passed_time":8.979565483,"remaining_time":3.338082642},
{"learn":[0.0005948423],"iteration":729,"passed_time":8.992603699,"remaining_time":3.326031505},
{"learn":[0.0005948351062],"iteration":730,"passed_time":9.003926847,"remaining_time":3.313346541},
{"learn":[0.0005948351062],"iteration":731,"passed_time":9.013495957,"remaining_time":3.30002311},
{"learn":[0.000594825974],"iteration":732,"passed_time":9.025870154,"remaining_time":3.287731693},
{"learn":[0.0005948368669],"iteration":733,"passed_time":9.039194881,"remaining_time":3.275784521},
{"learn":[0.000594832821],"iteration":734,"passed_time":9.049149074,"remaining_time":3.262618374},
{"learn":[0.000594816784],"iteration":735,"passed_time":9.060940432,"remaining_time":3.250119938},
{"learn":[0.000594817073],"iteration":736,"passed_time":9.070408977,"remaining_time":3.23679452},
{"learn":[0.0005948155125],"iteration":737,"passed_time":9.079723026,"remaining_time":3.223424706},
{"learn":[0.000594816175],"iteration":738,"passed_time":9.089914497,"remaining_time":3.210375756},
{"learn":[0.0005948192383],"iteration":739,"passed_time":9.100071699,"remaining_time":3.197322489},
{"learn":[0.0005947993556],"iteration":740,"passed_time":9.113592832,"remaining_time":3.185452825},
{"learn":[0.0005947881427],"iteration":741,"passed_time":9.127338171,"remaining_time":3.173656669},
{"learn":[0.0005947872179],"iteration":742,"passed_time":9.140139837,"remaining_time":3.161528854},
{"learn":[0.0005947898189],"iteration":743,"passed_time":9.150625122,"remaining_time":3.148602192},
{"learn":[0.0005947928822],"iteration":744,"passed_time":9.162814885,"remaining_time":3.136265498},
{"learn":[0.0005947981108],"iteration":745,"passed_time":9.171414725,"remaining_time":3.12270689},
{"learn":[0.0005947942693],"iteration":746,"passed_time":9.181633747,"remaining_time":3.109709957},
{"learn":[0.0005947924198],"iteration":747,"passed_time":9.196333288,"remaining_time":3.098229931},
{"learn":[0.0005947852528],"iteration":748,"passed_time":9.215096033,"remaining_time":3.088102943},
{"learn":[0.000594790917],"iteration":749,"passed_time":9.230615693,"remaining_time":3.076871898},
{"learn":[0.0005947784058],"iteration":750,"passed_time":9.235515182,"remaining_time":3.06210823},
{"learn":[0.0005947626535],"iteration":751,"passed_time":9.245364763,"remaining_time":3.049003273},
{"learn":[0.0005947697049],"iteration":752,"passed_time":9.249532522,"remaining_time":3.034043204},
{"learn":[0.0005947594436],"iteration":753,"passed_time":9.257997555,"remaining_time":3.020513791},
{"learn":[0.0005947539259],"iteration":754,"passed_time":9.267215021,"remaining_time":3.00724196},
{"learn":[0.0005947499956],"iteration":755,"passed_time":9.27299731,"remaining_time":2.992872148},
{"learn":[0.0005947331762],"iteration":756,"passed_time":9.278801537,"remaining_time":2.978532065},
{"learn":[0.0005947198825],"iteration":757,"passed_time":9.286188295,"remaining_time":2.964719746},
{"learn":[0.0005947245642],"iteration":758,"passed_time":9.298449048,"remaining_time":2.952471964},
{"learn":[0.0005947164724],"iteration":759,"passed_time":9.308154672,"remaining_time":2.939417265},
{"learn":[0.0005947130623],"iteration":760,"passed_time":9.323400503,"remaining_time":2.928111328},
{"learn":[0.0005947130623],"iteration":761,"passed_time":9.33802625,"remaining_time":2.916601375},
{"learn":[0.0005947252888],"iteration":762,"passed_time":9.349160475,"remaining_time":2.903998732},
{"learn":[0.0005946972055],"iteration":763,"passed_time":9.36205143,"remaining_time":2.891942588},
{"learn":[0.0005947071],"iteration":764,"passed_time":9.382507218,"remaining_time":2.8822081},
{"learn":[0.0005946963184],"iteration":765,"passed_time":9.389268339,"remaining_time":2.86826213},
{"learn":[0.0005946963184],"iteration":766,"passed_time":9.401537515,"remaining_time":2.856008137},
{"learn":[0.0005946925037],"iteration":767,"passed_time":9.420015461,"remaining_time":2.845629671},
{"learn":[0.0005946988038],"iteration":768,"passed_time":9.429556614,"remaining_time":2.832545615},
{"learn":[0.0005946850477],"iteration":769,"passed_time":9.442366151,"remaining_time":2.820447032},
{"learn":[0.0005946908854],"iteration":770,"passed_time":9.448514598,"remaining_time":2.806368149},
{"learn":[0.0005946906542],"iteration":771,"passed_time":9.46259283,"remaining_time":2.794651768},
{"learn":[0.0005946740082],"iteration":772,"passed_time":9.470112608,"remaining_time":2.781003314},
{"learn":[0.0005946740082],"iteration":773,"passed_time":9.476742321,"remaining_time":2.767110807},
{"learn":[0.0005946740082],"iteration":774,"passed_time":9.487112379,"remaining_time":2.754322949},
{"learn":[0.0005946773337],"iteration":775,"passed_time":9.499345094,"remaining_time":2.742078996},
{"learn":[0.0005946703091],"iteration":776,"passed_time":9.514735411,"remaining_time":2.730741309},
{"learn":[0.0005946545879],"iteration":777,"passed_time":9.528413429,"remaining_time":2.718904603},
{"learn":[0.0005946500796],"iteration":778,"passed_time":9.537460437,"remaining_time":2.705749367},
{"learn":[0.0005946477676],"iteration":779,"passed_time":9.546405154,"remaining_time":2.692575813},
{"learn":[0.0005946372483],"iteration":780,"passed_time":9.551762256,"remaining_time":2.678407086},
{"learn":[0.0005946356299],"iteration":781,"passed_time":9.576559505,"remaining_time":2.669680271},
{"learn":[0.0005946212959],"iteration":782,"passed_time":9.587863018,"remaining_time":2.657172765},
{"learn":[0.0005946212959],"iteration":783,"passed_time":9.601063964,"remaining_time":2.645191092},
{"learn":[0.0005946058636],"iteration":784,"passed_time":9.613091062,"remaining_time":2.632884813},
{"learn":[0.0005945918764],"iteration":785,"passed_time":9.620816292,"remaining_time":2.619407998},
{"learn":[0.0005945936992],"iteration":786,"passed_time":9.644089461,"remaining_time":2.610153819},
{"learn":[0.0005945900268],"iteration":787,"passed_time":9.658768591,"remaining_time":2.598551956},
{"learn":[0.0005945727183],"iteration":788,"passed_time":9.677141498,"remaining_time":2.587930109},
{"learn":[0.0005945771955],"iteration":789,"passed_time":9.691403987,"remaining_time":2.576195996},
{"learn":[0.0005945904314],"iteration":790,"passed_time":9.70780144,"remaining_time":2.565019597},
{"learn":[0.0005945696239],"iteration":791,"passed_time":9.717538615,"remaining_time":2.552080848},
{"learn":[0.0005945756928],"iteration":792,"passed_time":9.738011028,"remaining_time":2.541952437},
{"learn":[0.000594566414],"iteration":793,"passed_time":9.74326587,"remaining_time":2.527849835},
{"learn":[0.0005945795585],"iteration":794,"passed_time":9.74874309,"remaining_time":2.513826834},
{"learn":[0.0005945718403],"iteration":795,"passed_time":9.753927265,"remaining_time":2.499750204},
{"learn":[0.0005945480273],"iteration":796,"passed_time":9.807620856,"remaining_time":2.498051485},
{"learn":[0.0005945491254],"iteration":797,"passed_time":9.81754612,"remaining_time":2.485143253},
{"learn":[0.0005945478271],"iteration":798,"passed_time":9.837222094,"remaining_time":2.47469542},
{"learn":[0.0005945569283],"iteration":799,"passed_time":9.855199182,"remaining_time":2.463799795},
{"learn":[0.0005945418739],"iteration":800,"passed_time":9.870183588,"remaining_time":2.452142989},
{"learn":[0.000594541785],"iteration":801,"passed_time":9.880967725,"remaining_time":2.43944091},
{"learn":[0.0005945394731],"iteration":802,"passed_time":9.888839889,"remaining_time":2.426029213},
{"learn":[0.0005945385483],"iteration":803,"passed_time":9.906709088,"remaining_time":2.415068385},
{"learn":[0.0005945360052],"iteration":804,"passed_time":9.912788067,"remaining_time":2.401234376},
{"learn":[0.0005945410914],"iteration":805,"passed_time":9.923624335,"remaining_time":2.388564666},
{"learn":[0.0005945299941],"iteration":806,"passed_time":9.928659114,"remaining_time":2.374512031},
{"learn":[0.0005945243566],"iteration":807,"passed_time":9.932021735,"remaining_time":2.360084373},
{"learn":[0.0005945259482],"iteration":808,"passed_time":9.935637857,"remaining_time":2.345743919},
{"learn":[0.0005945222491],"iteration":809,"passed_time":9.938831928,"remaining_time":2.331330946},
{"learn":[0.0005945303677],"iteration":810,"passed_time":9.941804411,"remaining_time":2.316894},
{"learn":[0.0005945287225],"iteration":811,"passed_time":9.944609864,"remaining_time":2.302446619},
{"learn":[0.0005945128857],"iteration":812,"passed_time":9.948001657,"remaining_time":2.288162743},
{"learn":[0.0005945097646],"iteration":813,"passed_time":9.950938887,"remaining_time":2.27380176},
{"learn":[0.0005945187812],"iteration":814,"passed_time":9.953839925,"remaining_time":2.259460596},
{"learn":[0.0005945034913],"iteration":815,"passed_time":9.956818378,"remaining_time":2.245164928},
{"learn":[0.0005945060077],"iteration":816,"passed_time":9.959522809,"remaining_time":2.230835586},
{"learn":[0.0005945071059],"iteration":817,"passed_time":9.962327312,"remaining_time":2.216556933},
{"learn":[0.0005945071059],"iteration":818,"passed_time":9.965158854,"remaining_time":2.202312274},
{"learn":[0.0005945114986],"iteration":819,"passed_time":9.968095691,"remaining_time":2.188118566},
{"learn":[0.0005945141573],"iteration":820,"passed_time":9.970955929,"remaining_time":2.17393558},
{"learn":[0.000594502482],"iteration":821,"passed_time":9.973893245,"remaining_time":2.159796834},
{"learn":[0.0005944958662],"iteration":822,"passed_time":9.976984461,"remaining_time":2.145718408},
{"learn":[0.0005944857204],"iteration":823,"passed_time":9.979905949,"remaining_time":2.131630397},
{"learn":[0.0005944857204],"iteration":824,"passed_time":9.983000656,"remaining_time":2.1176062},
{"learn":[0.0005944815589],"iteration":825,"passed_time":9.98583147,"remaining_time":2.103552876},
{"learn":[0.0005944837552],"iteration":826,"passed_time":9.989365264,"remaining_time":2.089673749},
{"learn":[0.00059448468],"iteration":827,"passed_time":9.992260366,"remaining_time":2.075686936},
{"learn":[0.0005944850268],"iteration":828,"passed_time":9.995391526,"remaining_time":2.061775574},
{"learn":[0.0005944703459],"iteration":829,"passed_time":9.999349887,"remaining_time":2.048059615},
{"learn":[0.0005944776864],"iteration":830,"passed_time":10.00822192,"remaining_time":2.035366431},
{"learn":[0.0005944693634],"iteration":831,"passed_time":10.01490452,"remaining_time":2.022240336},
{"learn":[0.0005944732937],"iteration":832,"passed_time":10.02548006,"remaining_time":2.009910169},
{"learn":[0.0005944772818],"iteration":833,"passed_time":10.03276326,"remaining_time":1.996928898},
{"learn":[0.0005944570523],"iteration":834,"passed_time":10.03979884,"remaining_time":1.983912346},
{"learn":[0.0005944612138],"iteration":835,"passed_time":10.04764162,"remaining_time":1.971068452},
{"learn":[0.000594459422],"iteration":836,"passed_time":10.05559869,"remaining_time":1.958258765},
{"learn":[0.0005944524284],"iteration":837,"passed_time":10.05926662,"remaining_time":1.944631494},
{"learn":[0.0005944576035],"iteration":838,"passed_time":10.06241174,"remaining_time":1.930927641},
{"learn":[0.0005944523706],"iteration":839,"passed_time":10.0651162,"remaining_time":1.917164991},
{"learn":[0.0005944515036],"iteration":840,"passed_time":10.06786698,"remaining_time":1.903437396},
{"learn":[0.0005944422558],"iteration":841,"passed_time":10.07069827,"remaining_time":1.889750981},
{"learn":[0.0005944445678],"iteration":842,"passed_time":10.0737391,"remaining_time":1.876129346},
{"learn":[0.0005944339328],"iteration":843,"passed_time":10.0771263,"remaining_time":1.862596804},
{"learn":[0.0005944339328],"iteration":844,"passed_time":10.07947947,"remaining_time":1.848898601},
{"learn":[0.0005944290199],"iteration":845,"passed_time":10.08565799,"remaining_time":1.835923558},
{"learn":[0.0005944290199],"iteration":846,"passed_time":10.09458506,"remaining_time":1.823461055},
{"learn":[0.0005944338483],"iteration":847,"passed_time":10.10358655,"remaining_time":1.81102023},
{"learn":[0.0005944298669],"iteration":848,"passed_time":10.11024105,"remaining_time":1.798170081},
{"learn":[0.0005944250118],"iteration":849,"passed_time":10.11954977,"remaining_time":1.7858029},
{"learn":[0.000594425532],"iteration":850,"passed_time":10.13142374,"remaining_time":1.773892054},
{"learn":[0.0005944137411],"iteration":851,"passed_time":10.14307337,"remaining_time":1.761942323},
{"learn":[0.0005944037419],"iteration":852,"passed_time":10.14744616,"remaining_time":1.748739256},
{"learn":[0.0005944037419],"iteration":853,"passed_time":10.16240852,"remaining_time":1.737367264},
{"learn":[0.0005944037419],"iteration":854,"passed_time":10.16693004,"remaining_time":1.724216205},
{"learn":[0.0005944037419],"iteration":855,"passed_time":10.17239778,"remaining_time":1.711244486},
{"learn":[0.0005944037419],"iteration":856,"passed_time":10.18122381,"remaining_time":1.698850647},
{"learn":[0.0005944037419],"iteration":857,"passed_time":10.19100737,"remaining_time":1.686623598},
{"learn":[0.0005944037419],"iteration":858,"passed_time":10.20372389,"remaining_time":1.674883666},
{"learn":[0.0005944037419],"iteration":859,"passed_time":10.21701888,"remaining_time":1.663235632},
{"learn":[0.0005944037419],"iteration":860,"passed_time":10.228132,"remaining_time":1.651231531},
{"learn":[0.0005944037419],"iteration":861,"passed_time":10.23809898,"remaining_time":1.639046008},
{"learn":[0.0005944037419],"iteration":862,"passed_time":10.24349855,"remaining_time":1.626140558},
{"learn":[0.0005944037419],"iteration":863,"passed_time":10.24902964,"remaining_time":1.613273184},
{"learn":[0.0005944130475],"iteration":864,"passed_time":10.25629586,"remaining_time":1.600693573},
{"learn":[0.0005944130475],"iteration":865,"passed_time":10.26058064,"remaining_time":1.587664903},
{"learn":[0.0005944055647],"iteration":866,"passed_time":10.26814657,"remaining_time":1.575159738},
{"learn":[0.0005944075098],"iteration":867,"passed_time":10.28128213,"remaining_time":1.563512951},
{"learn":[0.0005944134321],"iteration":868,"passed_time":10.29229315,"remaining_time":1.551542465},
{"learn":[0.0005943974796],"iteration":869,"passed_time":10.30878613,"remaining_time":1.54039333},
{"learn":[0.0005943974796],"iteration":870,"passed_time":10.31339495,"remaining_time":1.527471812},
{"learn":[0.0005943997338],"iteration":871,"passed_time":10.31722743,"remaining_time":1.514455403},
{"learn":[0.000594397333],"iteration":872,"passed_time":10.32050216,"remaining_time":1.501378894},
{"learn":[0.0005944012055],"iteration":873,"passed_time":10.32390396,"remaining_time":1.488343134},
{"learn":[0.0005943951409],"iteration":874,"passed_time":10.32656215,"remaining_time":1.475223165},
{"learn":[0.0005943951677],"iteration":875,"passed_time":10.32933464,"remaining_time":1.46214326},
{"learn":[0.0005943790729],"iteration":876,"passed_time":10.33213919,"remaining_time":1.449091358},
{"learn":[0.0005943730886],"iteration":877,"passed_time":10.33485935,"remaining_time":1.436051071},
{"learn":[0.0005943696207],"iteration":878,"passed_time":10.33752194,"remaining_time":1.423026342},
{"learn":[0.0005943782327],"iteration":879,"passed_time":10.34267812,"remaining_time":1.410365198},
{"learn":[0.0005943782327],"iteration":880,"passed_time":10.34581419,"remaining_time":1.397448227},
{"learn":[0.0005943782327],"iteration":881,"passed_time":10.34941136,"remaining_time":1.384615125},
{"learn":[0.0005943654592],"iteration":882,"passed_time":10.3523438,"remaining_time":1.371714864},
{"learn":[0.0005943541307],"iteration":883,"passed_time":10.35645188,"remaining_time":1.358991423},
{"learn":[0.0005943596216],"iteration":884,"passed_time":10.36064226,"remaining_time":1.346298147},
{"learn":[0.0005943399122],"iteration":885,"passed_time":10.36625085,"remaining_time":1.333806543},
{"learn":[0.0005943477151],"iteration":886,"passed_time":10.37041487,"remaining_time":1.321146426},
{"learn":[0.0005943385251],"iteration":887,"passed_time":10.37564448,"remaining_time":1.308639844},
{"learn":[0.0005943385251],"iteration":888,"passed_time":10.37847873,"remaining_time":1.29585055},
{"learn":[0.0005943424554],"iteration":889,"passed_time":10.38127585,"remaining_time":1.283079037},
{"learn":[0.0005943238442],"iteration":890,"passed_time":10.38405521,"remaining_time":1.270327742},
{"learn":[0.0005943335544],"iteration":891,"passed_time":10.3867571,"remaining_time":1.257589424},
{"learn":[0.0005943273121],"iteration":892,"passed_time":10.38919856,"remaining_time":1.244842381},
{"learn":[0.0005943293929],"iteration":893,"passed_time":10.39166591,"remaining_time":1.232121461},
{"learn":[0.000594325347],"iteration":894,"passed_time":10.39493281,"remaining_time":1.219517257},
{"learn":[0.0005943303177],"iteration":895,"passed_time":10.39753499,"remaining_time":1.20685674},
{"learn":[0.000594315837],"iteration":896,"passed_time":10.40001329,"remaining_time":1.194204425},
{"learn":[0.0005943133827],"iteration":897,"passed_time":10.40245239,"remaining_time":1.181570316},
{"learn":[0.0005943223104],"iteration":898,"passed_time":10.40495956,"remaining_time":1.168966536},
{"learn":[0.0005943223104],"iteration":899,"passed_time":10.40725393,"remaining_time":1.156361547},
{"learn":[0.0005943223104],"iteration":900,"passed_time":10.40958623,"remaining_time":1.143783614},
{"learn":[0.0005943166772],"iteration":901,"passed_time":10.4130807,"remaining_time":1.131354666},
{"learn":[0.0005943197983],"iteration":902,"passed_time":10.41566381,"remaining_time":1.118847608},
{"learn":[0.0005943000312],"iteration":903,"passed_time":10.41821893,"remaining_time":1.106359532},
{"learn":[0.0005943000312],"iteration":904,"passed_time":10.42083832,"remaining_time":1.093900155},
{"learn":[0.0005942998578],"iteration":905,"passed_time":10.42333416,"remaining_time":1.081449682},
{"learn":[0.0005943070826],"iteration":906,"passed_time":10.42617014,"remaining_time":1.069056035},
{"learn":[0.0005942970257],"iteration":907,"passed_time":10.42861757,"remaining_time":1.056644071},
{"learn":[0.0005942874043],"iteration":908,"passed_time":10.43122425,"remaining_time":1.044269974},
{"learn":[0.0005942820558],"iteration":909,"passed_time":10.43364542,"remaining_time":1.031898998},
{"learn":[0.0005942895119],"iteration":910,"passed_time":10.43616394,"remaining_time":1.019559375},
{"learn":[0.0005942815089],"iteration":911,"passed_time":10.43877507,"remaining_time":1.007250226},
{"learn":[0.000594274253],"iteration":912,"passed_time":10.44114992,"remaining_time":0.9949398061},
{"learn":[0.0005942809509],"iteration":913,"passed_time":10.44359342,"remaining_time":0.9826575868},
{"learn":[0.0005942772786],"iteration":914,"passed_time":10.44605795,"remaining_time":0.9703988261},
{"learn":[0.000594267684],"iteration":915,"passed_time":10.44969777,"remaining_time":0.9582692277},
{"learn":[0.0005942650253],"iteration":916,"passed_time":10.45572942,"remaining_time":0.9463746366},
{"learn":[0.00059426563],"iteration":917,"passed_time":10.46148696,"remaining_time":0.9344683342},
{"learn":[0.0005942710363],"iteration":918,"passed_time":10.46489726,"remaining_time":0.9223685289},
{"learn":[0.0005942639849],"iteration":919,"passed_time":10.46989223,"remaining_time":0.9104254112},
{"learn":[0.0005942639849],"iteration":920,"passed_time":10.47422284,"remaining_time":0.8984403959},
{"learn":[0.0005942488417],"iteration":921,"passed_time":10.47965454,"remaining_time":0.8865651348},
{"learn":[0.0005942536968],"iteration":922,"passed_time":10.48400532,"remaining_time":0.8746136613},
{"learn":[0.0005942536968],"iteration":923,"passed_time":10.48873552,"remaining_time":0.8627098483},
{"learn":[0.0005942384957],"iteration":924,"passed_time":10.49285053,"remaining_time":0.8507716649},
{"learn":[0.0005942368196],"iteration":925,"passed_time":10.49744676,"remaining_time":0.8388888341},
{"learn":[0.0005942445956],"iteration":926,"passed_time":10.50241237,"remaining_time":0.8270508122},
{"learn":[0.0005942445956],"iteration":927,"passed_time":10.50671042,"remaining_time":0.8151758087},
{"learn":[0.0005942385535],"iteration":928,"passed_time":10.51077735,"remaining_time":0.8032994528},
{"learn":[0.0005942383223],"iteration":929,"passed_time":10.51317945,"remaining_time":0.7913145826},
{"learn":[0.0005942295369],"iteration":930,"passed_time":10.51544049,"remaining_time":0.7793398429},
{"learn":[0.0005942296525],"iteration":931,"passed_time":10.51757944,"remaining_time":0.767377041},
{"learn":[0.0005942244239],"iteration":932,"passed_time":10.51985524,"remaining_time":0.7554451246},
{"learn":[0.0005942334672],"iteration":933,"passed_time":10.52204637,"remaining_time":0.7435279021},
{"learn":[0.0005942177728],"iteration":934,"passed_time":10.52422932,"remaining_time":0.7316309151},
{"learn":[0.0005942064175],"iteration":935,"passed_time":10.52637902,"remaining_time":0.7197524117},
{"learn":[0.000594210579],"iteration":936,"passed_time":10.52868727,"remaining_time":0.7079053343},
{"learn":[0.0005942071111],"iteration":937,"passed_time":10.53087309,"remaining_time":0.6960705028},
{"learn":[0.0005942124286],"iteration":938,"passed_time":10.53316912,"remaining_time":0.6842633825},
{"learn":[0.0005941974587],"iteration":939,"passed_time":10.53525244,"remaining_time":0.6724629214},
{"learn":[0.0005941917634],"iteration":940,"passed_time":10.53754361,"remaining_time":0.6606961458},
{"learn":[0.0005942001175],"iteration":941,"passed_time":10.5401476,"remaining_time":0.6489687483},
{"learn":[0.0005941845118],"iteration":942,"passed_time":10.54294468,"remaining_time":0.6372723721},
{"learn":[0.0005941874596],"iteration":943,"passed_time":10.54557521,"remaining_time":0.6255849699},
{"learn":[0.0005941832135],"iteration":944,"passed_time":10.54815892,"remaining_time":0.6139140114},
{"learn":[0.0005941838183],"iteration":945,"passed_time":10.5502648,"remaining_time":0.6022349888},
{"learn":[0.0005941667677],"iteration":946,"passed_time":10.5522855,"remaining_time":0.5905714165},
{"learn":[0.0005941645713],"iteration":947,"passed_time":10.55431099,"remaining_time":0.5789284509},
{"learn":[0.0005941613078],"iteration":948,"passed_time":10.5564048,"remaining_time":0.5673094258},
{"learn":[0.0005941706402],"iteration":949,"passed_time":10.55859105,"remaining_time":0.5557153182},
{"learn":[0.0005941641089],"iteration":950,"passed_time":10.56074598,"remaining_time":0.5441393825},
{"learn":[0.0005941628374],"iteration":951,"passed_time":10.56286459,"remaining_time":0.5325814079},
{"learn":[0.0005941586759],"iteration":952,"passed_time":10.56496605,"remaining_time":0.5210423969},
{"learn":[0.0005941458756],"iteration":953,"passed_time":10.56712161,"remaining_time":0.50952578},
{"learn":[0.0005941433014],"iteration":954,"passed_time":10.56916345,"remaining_time":0.4980234087},
{"learn":[0.0005941370592],"iteration":955,"passed_time":10.57113892,"remaining_time":0.4865377746},
{"learn":[0.0005941310481],"iteration":956,"passed_time":10.57315356,"remaining_time":0.4750737756},
{"learn":[0.0005941324621],"iteration":957,"passed_time":10.57527496,"remaining_time":0.4636341842},
{"learn":[0.0005941294298],"iteration":958,"passed_time":10.57724184,"remaining_time":0.4522074198},
{"learn":[0.000594129083],"iteration":959,"passed_time":10.57924945,"remaining_time":0.4408020606},
{"learn":[0.000594129083],"iteration":960,"passed_time":10.58120386,"remaining_time":0.4294141003},
{"learn":[0.0005941243745],"iteration":961,"passed_time":10.58320956,"remaining_time":0.418047779},
{"learn":[0.000594115796],"iteration":962,"passed_time":10.58538537,"remaining_time":0.4067074338},
{"learn":[0.0005941198152],"iteration":963,"passed_time":10.58740703,"remaining_time":0.3953803457},
{"learn":[0.0005941168096],"iteration":964,"passed_time":10.58934752,"remaining_time":0.384069599},
{"learn":[0.0005941076775],"iteration":965,"passed_time":10.59142711,"remaining_time":0.3727831487},
{"learn":[0.0005941114033],"iteration":966,"passed_time":10.59351398,"remaining_time":0.3615159889},
{"learn":[0.0005941057123],"iteration":967,"passed_time":10.59551003,"remaining_time":0.3502647945},
{"learn":[0.0005941210867],"iteration":968,"passed_time":10.59830988,"remaining_time":0.3390584173},
{"learn":[0.0005941038895],"iteration":969,"passed_time":10.60033397,"remaining_time":0.3278453804},
{"learn":[0.0005941071573],"iteration":970,"passed_time":10.60227722,"remaining_time":0.3166488563},
{"learn":[0.0005940879103],"iteration":971,"passed_time":10.60430545,"remaining_time":0.3054738195},
{"learn":[0.0005941012618],"iteration":972,"passed_time":10.60642677,"remaining_time":0.2943201674},
{"learn":[0.0005940871012],"iteration":973,"passed_time":10.60846621,"remaining_time":0.2831828761},
{"learn":[0.0005940828508],"iteration":974,"passed_time":10.61039505,"remaining_time":0.2720614114},
{"learn":[0.0005940828508],"iteration":975,"passed_time":10.61244112,"remaining_time":0.2609616669},
{"learn":[0.000594085972],"iteration":976,"passed_time":10.61451778,"remaining_time":0.2498811759},
{"learn":[0.000594084558],"iteration":977,"passed_time":10.61652489,"remaining_time":0.2388175333},
{"learn":[0.0005940756838],"iteration":978,"passed_time":10.61862786,"remaining_time":0.2277744486},
{"learn":[0.0005940751101],"iteration":979,"passed_time":10.6206948,"remaining_time":0.2167488736},
{"learn":[0.0005940817837],"iteration":980,"passed_time":10.62262507,"remaining_time":0.2057389156},
{"learn":[0.0005940760038],"iteration":981,"passed_time":10.62471596,"remaining_time":0.1947503943},
{"learn":[0.0005940748789],"iteration":982,"passed_time":10.62668857,"remaining_time":0.1837779305},
{"learn":[0.0005940793561],"iteration":983,"passed_time":10.62863207,"remaining_time":0.1728232857},
{"learn":[0.0005940614386],"iteration":984,"passed_time":10.63074032,"remaining_time":0.1618894464},
{"learn":[0.0005940547339],"iteration":985,"passed_time":10.63293911,"remaining_time":0.1509747947},
{"learn":[0.0005940539558],"iteration":986,"passed_time":10.63496523,"remaining_time":0.1400755299},
{"learn":[0.0005940632614],"iteration":987,"passed_time":10.63706722,"remaining_time":0.1291951484},
{"learn":[0.0005940547339],"iteration":988,"passed_time":10.6391469,"remaining_time":0.1183322708},
{"learn":[0.0005940376523],"iteration":989,"passed_time":10.64121068,"remaining_time":0.1074869765},
{"learn":[0.000594042365],"iteration":990,"passed_time":10.64345922,"remaining_time":0.09666108275},
{"learn":[0.0005940413514],"iteration":991,"passed_time":10.64549842,"remaining_time":0.08585079374},
{"learn":[0.0005940483761],"iteration":992,"passed_time":10.64763305,"remaining_time":0.07505884328},
{"learn":[0.0005940249987],"iteration":993,"passed_time":10.64965052,"remaining_time":0.06428360476},
{"learn":[0.000594034589],"iteration":994,"passed_time":10.65168445,"remaining_time":0.05352605251},
{"learn":[0.0005940207751],"iteration":995,"passed_time":10.65381782,"remaining_time":0.04278641696},
{"learn":[0.0005940207484],"iteration":996,"passed_time":10.65585409,"remaining_time":0.03206375354},
{"learn":[0.0005940212686],"iteration":997,"passed_time":10.65784607,"remaining_time":0.02135840897},
{"learn":[0.0005940010968],"iteration":998,"passed_time":10.65988953,"remaining_time":0.01067056009},
{"learn":[0.0005940193612],"iteration":999,"passed_time":10.6619229,"remaining_time":0}
]},"iteration":999,"passed_time":10.4637312,"remaining_time":0}
]}